Workbook
Name \P: '[1]JULY-06'!#REF!
Name \P: '[1]JULY-06'!#REF!
Name \P: '[1]JULY-06'!#REF!
Name \P: '[1]JULY-06'!#REF!
Name \P: '[1]JULY-06'!#REF!
Name _: '[2]P&L, CF and Notes'!#REF!
Name _: '[2]P&L, CF and Notes'!#REF!
Name _: '[2]P&L, CF and Notes'!#REF!
Name _: '[2]P&L, CF and Notes'!#REF!
Name _: '[2]P&L, CF and Notes'!#REF!
Name _______lkm2: #N/A
Name ______J439643: [3]Notes!#REF!
Name ______J439643: [3]Notes!#REF!
Name ______J439643: [3]Notes!#REF!
Name ______J439643: [3]Notes!#REF!
Name ______J439643: [3]Notes!#REF!
Name ______lkm2: #N/A
Name _____J439643: [3]Notes!#REF!
Name _____J439643: [3]Notes!#REF!
Name _____J439643: [3]Notes!#REF!
Name _____J439643: [3]Notes!#REF!
Name _____J439643: [3]Notes!#REF!
Name _____RSE1: #REF!
Name _____RSE1: #REF!
Name _____RSE1: #REF!
Name _____RSE1: #REF!
Name _____RSE1: #REF!
Name _____RSE2: #REF!
Name _____RSE2: #REF!
Name _____RSE2: #REF!
Name _____RSE2: #REF!
Name _____RSE2: #REF!
Name ____DEC97: [4]SPIN!$A$105:$I$106
Name ____FEB98: [4]SPIN!$A$155:$I$156
Name ____JAN98: [4]SPIN!$A$135:$I$136
Name ____lkm2: #N/A
Name ____MAR98: [4]SPIN!$A$180:$I$181
Name ____MAY98: [4]SPIN!$A$237:$I$238
Name ____NOV97: [4]SPIN!$A$73:$I$74
Name ____OCT97: [4]SPIN!$A$40:$I$41
Name ____RSE1: #REF!
Name ____RSE1: #REF!
Name ____RSE1: #REF!
Name ____RSE1: #REF!
Name ____RSE1: #REF!
Name ____RSE2: #REF!
Name ____RSE2: #REF!
Name ____RSE2: #REF!
Name ____RSE2: #REF!
Name ____RSE2: #REF!
Name ____T2: '[5]Sugar tax dep'!$L$29
Name ___DEC97: [4]SPIN!$A$105:$I$106
Name ___FEB98: [4]SPIN!$A$155:$I$156
Name ___J439643: [3]Notes!#REF!
Name ___J439643: [3]Notes!#REF!
Name ___J439643: [3]Notes!#REF!
Name ___J439643: [3]Notes!#REF!
Name ___J439643: [3]Notes!#REF!
Name ___JAN98: [4]SPIN!$A$135:$I$136
Name ___MAR98: [4]SPIN!$A$180:$I$181

Sheet Cover
G2: 1 | H2: 2 | I2: 3 | J2: 4 | K2: 5 | L2: 6 | M2: 7 | N2: 8 | O2: 9 | P2: 10 | Q2: 11
C3: 1 | I3: Months | J3: Current | K3: Last Year | M3: Cummulative Months | N3: Days | O3: Cumm | P3: Heading | Q3: Budget
G4: 1 | I4: Current Month - January | J4: =+SOMCI!AB$9 -> 46023 | K4: 45658 | L4: 12/11 | M4: Cumulative 1 Months ended January | N4: 31 | O4: =N4 -> 31 | P4: =TEXT(J4,"mmmm-yyyy") -> January-2026 | Q4: 2026
G5: 2 | I5: Current Month - February | J5: =+SOMCI!Z$9 -> 45992 | K5: 45689 | L5: 12/11 | M5: Cumulative 2 Months ended February | N5: 28 | O5: =O4+N5 -> 59 | P5: =TEXT(J5,"mmmm-yyyy") -> December-2025 | Q5: 2026
G6: 3 | I6: Current Month - March | J6: =+SOMCI!J$9 -> 45748 | K6: 45717 | L6: 12/11 | M6: Cumulative 3 Months ended March | N6: 31 | O6: =O5+N6 -> 90 | P6: =TEXT(J6,"mmmm-yyyy") -> April-2025 | Q6: 2026
A7: ="Report Period " &TEXT(VLOOKUP($C$3,Date_data,4,),"MMMM - YYYY") -> Report Period January - 2026 | G7: 4 | I7: Current Month - April | J7: =+SOMCI!L$9 -> 45778 | K7: 45748 | L7: 12/11 | M7: Cumulative 4 Months ended April | N7: 30 | O7: =O6+N7 -> 120 | P7: =TEXT(J7,"mmmm-yyyy") -> May-2025 | Q7: 2026
G8: 5 | I8: Current Month - May | J8: =+SOMCI!N$9 -> 45809 | K8: 45778 | L8: 12/11 | M8: Cumulative 5 Months ended May | N8: 31 | O8: =O7+N8 -> 151 | P8: =TEXT(J8,"mmmm-yyyy") -> June-2025 | Q8: 2026
A9: Afrodiva Exotic Hair Boutique Ltd. | G9: 7 | I9: Current Month - July | J9: =+SOMCI!R$9 -> 45870 | K9: 45839 | L9: 12/11 | M9: Cumulative 7 Months ended July | N9: 31 | O9: =O8+N9 -> 182 | P9: =TEXT(J9,"mmmm-yyyy") -> August-2025 | Q9: 2026
A10: DUABI UAE | G10: 8 | I10: Current Month - August | J10: =+SOMCI!T$9 -> 45901 | K10: 45870 | L10: 12/11 | M10: Cumulative 8 Months ended August | N10: 31 | O10: =O9+N10 -> 213 | P10: =TEXT(J10,"mmmm-yyyy") -> September-2025 | Q10: 2026
G11: 9 | I11: Current Month - September | J11: =+SOMCI!V$9 -> 45931 | K11: 45901 | L11: 12/11 | M11: Cumulative 9 Months ended September | N11: 30 | O11: =O10+N11 -> 243 | P11: =TEXT(J11,"mmmm-yyyy") -> October-2025 | Q11: 2026
G12: 10 | I12: Current Month - October | J12: =+SOMCI!X$9 -> 45962 | K12: 45931 | L12: 12/11 | M12: Cumulative 10 Months ended October | N12: 31 | O12: =O11+N12 -> 274 | P12: =TEXT(J12,"mmmm-yyyy") -> November-2025 | Q12: 2026
G13: 11 | I13: Current Month - November | J13: =+SOMCI!Z$9 -> 45992 | K13: 45962 | L13: 12/11 | M13: Cumulative 11 Months ended November | N13: 30 | O13: =O12+N13 -> 304 | P13: =TEXT(J13,"mmmm-yyyy") -> December-2025 | Q13: 2026
G14: 12 | I14: Current Month - December | J14: =+SOMCI!AB$9 -> 46023 | K14: 45992 | L14: 12/11 | M14: Cumulative 12 Months ended December | N14: 31 | O14: =O13+N14 -> 335 | P14: =TEXT(J14,"mmmm-yyyy") -> January-2026 | Q14: 2026

Sheet Contents
A2: MARFA ACCOUNTING & BOOKKEEPING L.L.C
A3: Dubai, U.A.E
A4: URL:www.mataconsultancy.com E- h.ejaz@mataconsultancy.com Tel.: +971 50 673 0437
A6: =Cover!A9 -> Afrodiva Exotic Hair Boutique Ltd.
A7: =Cover!A10 -> DUABI UAE
A9: ="MIS Report Period " &TEXT(VLOOKUP(Cover!$C$3,Date_data,4,),"MMMM - YYYY") -> MIS Report Period January - 2026
A11: Table of Contents
B13: Contents | E13: Page#
B15: Galance | E15: =SUM(SUBTOTAL(103,$B$15:B15)+2) -> 3
B16: Observations & Recommendations | E16: =SUM(SUBTOTAL(103,$B$15:B16)+2) -> 4
B17: Key Performance Indicator - Comparison | E17: =SUM(SUBTOTAL(103,$B$15:B17)+2) -> 5
B18: Statement of Financial Position - Balance Sheet | E18: =SUM(SUBTOTAL(103,$B$15:B18)+2) -> 6
B19: Statement of Financial Position or Balance Sheet - Monthly | E19: =SUM(SUBTOTAL(103,$B$15:B19)+2) -> 7
B20: Statement of Comprehensive Income - Profit & Loss | E20: =SUM(SUBTOTAL(103,$B$15:B20)+2) -> 8
B21: Statement of Comprehensive Income or Profit & Loss Monthly | E21: =SUM(SUBTOTAL(103,$B$15:B21)+2) -> 9
B22: Statement of Cash Flow | E22: =SUM(SUBTOTAL(103,$B$15:B22)+2) -> 10
B23: Budget Variance Statement | E23: =SUM(SUBTOTAL(103,$B$15:B23)+2) -> 11
B24: Debitors Aging Summary | E24: =SUM(SUBTOTAL(103,$B$15:B24)+2) -> 12
B25: Bank & Cash Position / Reconciliation | E25: =SUM(SUBTOTAL(103,$B$15:B25)+2) -> 13

Sheet Observations & Recommendations 
A1: =Cover!$A$9 -> Afrodiva Exotic Hair Boutique Ltd.
A2: =Cover!$A$10 -> DUABI UAE
A3: Observations & Recommendations
A6: SR# | B6: Head | C6: Details | D6: Risk | E6: Recommendations | F6: Status
A7: 1
A8: 2
A9: 3
A10: 4
A11: 5

Sheet Galance
A2: =Cover!A9 -> Afrodiva Exotic Hair Boutique Ltd.
A3: =Cover!A10 -> DUABI UAE
B5: Galance Picture
B7: Balance Sheet Statement 6 Month Comparison | D7: ="As On "&TEXT(SOCI!$F$8,"MMMM - YYYY") -> As On January - 2026
B9: Particulars | C9: =VLOOKUP(Cover!$C$3,Cover!$G$4:$Q$15,4,) -> 46023 | D9: =DATE(YEAR(C9),MONTH(C9)-1,1) -> 45992 | E9: =DATE(YEAR(D9),MONTH(D9)-1,1) -> 45962 | F9: =DATE(YEAR(E9),MONTH(E9)-1,1) -> 45931 | G9: =DATE(YEAR(F9),MONTH(F9)-1,1) -> 45901 | H9: =DATE(YEAR(G9),MONTH(G9)-1,1) -> 45870
B11: ASSETS: | C11: =SUM(C12:C13) -> 0 | D11: =SUM(D12:D13) -> 0 | E11: =SUM(E12:E13) -> 0 | F11: =SUM(F12:F13) -> 0 | G11: =SUM(G12:G13) -> 0 | H11: =SUM(H12:H13) -> 0
B12: Fixed Assets | C12: =_xlfn.IFNA(INDEX(SOMFP!$E$10:$AB$49,MATCH(Galance!$B12,SOMFP!$A$10:$A$49,0),MATCH(Galance!C$9,SOMFP!$E$8:$AA$8,0)),0) -> 0 | D12: =_xlfn.IFNA(INDEX(SOMFP!$E$10:$AB$49,MATCH(Galance!$B12,SOMFP!$A$10:$A$49,0),MATCH(Galance!D$9,SOMFP!$E$8:$AA$8,0)),0) -> 0 | E12: =_xlfn.IFNA(INDEX(SOMFP!$E$10:$AB$49,MATCH(Galance!$B12,SOMFP!$A$10:$A$49,0),MATCH(Galance!E$9,SOMFP!$E$8:$AA$8,0)),0) -> 0 | F12: =_xlfn.IFNA(INDEX(SOMFP!$E$10:$AB$49,MATCH(Galance!$B12,SOMFP!$A$10:$A$49,0),MATCH(Galance!F$9,SOMFP!$E$8:$AA$8,0)),0) -> 0 | G12: =_xlfn.IFNA(INDEX(SOMFP!$E$10:$AB$49,MATCH(Galance!$B12,SOMFP!$A$10:$A$49,0),MATCH(Galance!G$9,SOMFP!$E$8:$AA$8,0)),0) -> 0 | H12: =_xlfn.IFNA(INDEX(SOMFP!$E$10:$AB$49,MATCH(Galance!$B12,SOMFP!$A$10:$A$49,0),MATCH(Galance!H$9,SOMFP!$E$8:$AA$8,0)),0) -> 0
B13: Current Assets | C13: =INDEX(SOMFP!$E$10:$AB$49,MATCH(Galance!$B13,SOMFP!$A$10:$A$49,0),MATCH(Galance!C$9,SOMFP!$E$8:$AA$8,0)) -> 0 | D13: =INDEX(SOMFP!$E$10:$AB$49,MATCH(Galance!$B13,SOMFP!$A$10:$A$49,0),MATCH(Galance!D$9,SOMFP!$E$8:$AA$8,0)) -> 0 | E13: =INDEX(SOMFP!$E$10:$AB$49,MATCH(Galance!$B13,SOMFP!$A$10:$A$49,0),MATCH(Galance!E$9,SOMFP!$E$8:$AA$8,0)) -> 0 | F13: =INDEX(SOMFP!$E$10:$AB$49,MATCH(Galance!$B13,SOMFP!$A$10:$A$49,0),MATCH(Galance!F$9,SOMFP!$E$8:$AA$8,0)) -> 0 | G13: =INDEX(SOMFP!$E$10:$AB$49,MATCH(Galance!$B13,SOMFP!$A$10:$A$49,0),MATCH(Galance!G$9,SOMFP!$E$8:$AA$8,0)) -> 0 | H13: =INDEX(SOMFP!$E$10:$AB$49,MATCH(Galance!$B13,SOMFP!$A$10:$A$49,0),MATCH(Galance!H$9,SOMFP!$E$8:$AA$8,0)) -> 0
B15: LIABILITIES: | C15: =SUM(C16:C17) -> 0 | D15: =SUM(D16:D17) -> 0 | E15: =SUM(E16:E17) -> 0 | F15: =SUM(F16:F17) -> 0 | G15: =SUM(G16:G17) -> 0 | H15: =SUM(H16:H17) -> 0
B16: Non-current Liabilities | C16: =-INDEX(SOMFP!$E$10:$AB$49,MATCH(Galance!$B16,SOMFP!$A$10:$A$49,0),MATCH(Galance!C$9,SOMFP!$E$8:$AA$8,0)) -> 0 | D16: =-INDEX(SOMFP!$E$10:$AB$49,MATCH(Galance!$B16,SOMFP!$A$10:$A$49,0),MATCH(Galance!D$9,SOMFP!$E$8:$AA$8,0)) -> 0 | E16: =-INDEX(SOMFP!$E$10:$AB$49,MATCH(Galance!$B16,SOMFP!$A$10:$A$49,0),MATCH(Galance!E$9,SOMFP!$E$8:$AA$8,0)) -> 0 | F16: =-INDEX(SOMFP!$E$10:$AB$49,MATCH(Galance!$B16,SOMFP!$A$10:$A$49,0),MATCH(Galance!F$9,SOMFP!$E$8:$AA$8,0)) -> 0 | G16: =-INDEX(SOMFP!$E$10:$AB$49,MATCH(Galance!$B16,SOMFP!$A$10:$A$49,0),MATCH(Galance!G$9,SOMFP!$E$8:$AA$8,0)) -> 0 | H16: =-INDEX(SOMFP!$E$10:$AB$49,MATCH(Galance!$B16,SOMFP!$A$10:$A$49,0),MATCH(Galance!H$9,SOMFP!$E$8:$AA$8,0)) -> 0
B17: Current liabilities | C17: =-INDEX(SOMFP!$E$10:$AB$49,MATCH(Galance!$B17,SOMFP!$A$10:$A$49,0),MATCH(Galance!C$9,SOMFP!$E$8:$AA$8,0)) -> 0 | D17: =-INDEX(SOMFP!$E$10:$AB$49,MATCH(Galance!$B17,SOMFP!$A$10:$A$49,0),MATCH(Galance!D$9,SOMFP!$E$8:$AA$8,0)) -> 0 | E17: =-INDEX(SOMFP!$E$10:$AB$49,MATCH(Galance!$B17,SOMFP!$A$10:$A$49,0),MATCH(Galance!E$9,SOMFP!$E$8:$AA$8,0)) -> 0 | F17: =-INDEX(SOMFP!$E$10:$AB$49,MATCH(Galance!$B17,SOMFP!$A$10:$A$49,0),MATCH(Galance!F$9,SOMFP!$E$8:$AA$8,0)) -> 0 | G17: =-INDEX(SOMFP!$E$10:$AB$49,MATCH(Galance!$B17,SOMFP!$A$10:$A$49,0),MATCH(Galance!G$9,SOMFP!$E$8:$AA$8,0)) -> 0 | H17: =-INDEX(SOMFP!$E$10:$AB$49,MATCH(Galance!$B17,SOMFP!$A$10:$A$49,0),MATCH(Galance!H$9,SOMFP!$E$8:$AA$8,0)) -> 0
B18: Net worth | C18: =+C11+C15 -> 0 | D18: =+D11+D15 -> 0 | E18: =+E11+E15 -> 0 | F18: =+F11+F15 -> 0 | G18: =+G11+G15 -> 0 | H18: =+H11+H15 -> 0
B20: Profit & Loss Statement 6 Month Comparison | D20: ="For the month of "&TEXT(SOCI!$F$8,"MMMM - YYYY") -> For the month of January - 2026
B22: Particulars | C22: =VLOOKUP(Cover!$C$3,Cover!$G$4:$Q$15,4,) -> 46023 | D22: =DATE(YEAR(C22),MONTH(C22)-1,1) -> 45992 | E22: =DATE(YEAR(D22),MONTH(D22)-1,1) -> 45962 | F22: =DATE(YEAR(E22),MONTH(E22)-1,1) -> 45931 | G22: =DATE(YEAR(F22),MONTH(F22)-1,1) -> 45901 | H22: =DATE(YEAR(G22),MONTH(G22)-1,1) -> 45870
B24: Revenue | C24: =INDEX(SOMCI!$F$12:$AD$51,MATCH(Galance!$B24,SOMCI!$A$12:$A$51,0),MATCH(Galance!C$22,SOMCI!$F$9:$AB$9,0)) -> 87643.893 | D24: =INDEX(SOMCI!$F$12:$AD$51,MATCH(Galance!$B24,SOMCI!$A$12:$A$51,0),MATCH(Galance!D$22,SOMCI!$F$9:$AB$9,0)) -> 0 | E24: =INDEX(SOMCI!$F$12:$AD$51,MATCH(Galance!$B24,SOMCI!$A$12:$A$51,0),MATCH(Galance!E$22,SOMCI!$F$9:$AB$9,0)) -> 0 | F24: =INDEX(SOMCI!$F$12:$AD$51,MATCH(Galance!$B24,SOMCI!$A$12:$A$51,0),MATCH(Galance!F$22,SOMCI!$F$9:$AB$9,0)) -> 0 | G24: =INDEX(SOMCI!$F$12:$AD$51,MATCH(Galance!$B24,SOMCI!$A$12:$A$51,0),MATCH(Galance!G$22,SOMCI!$F$9:$AB$9,0)) -> 0 | H24: =INDEX(SOMCI!$F$12:$AD$51,MATCH(Galance!$B24,SOMCI!$A$12:$A$51,0),MATCH(Galance!G$22,SOMCI!$J$9:$AB$9,0)) -> 0
B25: Direct Expenses | C25: =INDEX(SOMCI!$F$12:$AD$51,MATCH(Galance!$B25,SOMCI!$A$12:$A$51,0),MATCH(Galance!C$22,SOMCI!$F$9:$AB$9,0)) -> 35045.157 | D25: =INDEX(SOMCI!$F$12:$AD$51,MATCH(Galance!$B25,SOMCI!$A$12:$A$51,0),MATCH(Galance!D$22,SOMCI!$F$9:$AB$9,0)) -> 0 | E25: =INDEX(SOMCI!$F$12:$AD$51,MATCH(Galance!$B25,SOMCI!$A$12:$A$51,0),MATCH(Galance!E$22,SOMCI!$F$9:$AB$9,0)) -> 0 | F25: =INDEX(SOMCI!$F$12:$AD$51,MATCH(Galance!$B25,SOMCI!$A$12:$A$51,0),MATCH(Galance!F$22,SOMCI!$F$9:$AB$9,0)) -> 0 | G25: =INDEX(SOMCI!$F$12:$AD$51,MATCH(Galance!$B25,SOMCI!$A$12:$A$51,0),MATCH(Galance!G$22,SOMCI!$F$9:$AB$9,0)) -> 0 | H25: =INDEX(SOMCI!$F$12:$AD$51,MATCH(Galance!$B25,SOMCI!$A$12:$A$51,0),MATCH(Galance!H$22,SOMCI!$F$9:$AB$9,0)) -> 0
B26: Gross Profit / (Loss) | C26: =INDEX(SOMCI!$F$12:$AD$51,MATCH(Galance!$B26,SOMCI!$A$12:$A$51,0),MATCH(Galance!C$22,SOMCI!$F$9:$AB$9,0)) -> 52598.737 | D26: =+D24-D25 -> 0 | E26: =+E24-E25 -> 0 | F26: =+F24-F25 -> 0 | G26: =+G24-G25 -> 0 | H26: =+H24-H25 -> 0
B27: Indirect Expenses | C27: =INDEX(SOMCI!$F$12:$AD$51,MATCH(Galance!$B27,SOMCI!$A$12:$A$51,0),MATCH(Galance!C$22,SOMCI!$F$9:$AB$9,0)) -> 56797.81 | D27: =INDEX(SOMCI!$F$12:$AD$51,MATCH(Galance!$B27,SOMCI!$A$12:$A$51,0),MATCH(Galance!D$22,SOMCI!$F$9:$AB$9,0)) -> 0 | E27: =INDEX(SOMCI!$F$12:$AD$51,MATCH(Galance!$B27,SOMCI!$A$12:$A$51,0),MATCH(Galance!E$22,SOMCI!$F$9:$AB$9,0)) -> 0 | F27: =INDEX(SOMCI!$F$12:$AD$51,MATCH(Galance!$B27,SOMCI!$A$12:$A$51,0),MATCH(Galance!F$22,SOMCI!$F$9:$AB$9,0)) -> 0 | G27: =INDEX(SOMCI!$F$12:$AD$51,MATCH(Galance!$B27,SOMCI!$A$12:$A$51,0),MATCH(Galance!G$22,SOMCI!$F$9:$AB$9,0)) -> 0 | H27: =INDEX(SOMCI!$F$12:$AD$51,MATCH(Galance!$B27,SOMCI!$A$12:$A$51,0),MATCH(Galance!H$22,SOMCI!$F$9:$AB$9,0)) -> 0
B28: Net Profit / (Loss) | C28: =INDEX(SOMCI!$F$12:$AD$51,MATCH(Galance!$B28,SOMCI!$A$12:$A$51,0),MATCH(Galance!C$22,SOMCI!$F$9:$AB$9,0)) -> -16699.073 | D28: =+D26-D27 -> 0 | E28: =+E26-E27 -> 0 | F28: =+F26-F27 -> 0 | G28: =+G26-G27 -> 0 | H28: =+H26-H27 -> 0

Sheet KPI Comparisons
A2: =Cover!A9 -> Afrodiva Exotic Hair Boutique Ltd.
A3: =Cover!A10 -> DUABI UAE
A5: Key Performance Indicator - Comparison

Sheet SOFP
A2: =Cover!A9 -> Afrodiva Exotic Hair Boutique Ltd.
A3: =Cover!A10 -> DUABI UAE
A5: STATEMENT OF FINANCIAL POSITION
A6: =Galance!D7 -> As On January - 2026
A7: Amount in AED
A8: Particulars | C8: Note | E8: =+SOCI!F8 -> 46023 | H8: =+SOCI!I8 -> 45992 | I8: =DATE(YEAR(H8),MONTH(H8)-1,1) -> 45962
A9: Assets: | E9: DIFC | F9: Al Barsha
A10: Fixed Assets | E10: =SUM(E11:E13) -> 0 | F10: =SUM(F11:F13) -> 0 | H10: =SUM(H11:H13) -> 0 | I10: =SUM(I11:I13) -> 0
E11: =IFERROR(INDEX(SOMFP!$E$11:$AB$49,MATCH($B11,SOMFP!$B$11:$B$44,0),MATCH($E$8,SOMFP!$E$8:$AA$8,0)),"") | F11: =IFERROR(INDEX(SOMFP!$E$11:$AB$49,MATCH($B11,SOMFP!$B$11:$B$44,0),MATCH($E$8,SOMFP!$E$8:$AA$8,0)),"") | H11: =IFERROR(INDEX(SOMFP!$E$11:$AB$49,MATCH($B11,SOMFP!$B$11:$B$44,0),MATCH($H$8,SOMFP!$E$8:$AA$8,0)),"") | I11: =IFERROR(INDEX(SOMFP!$E$11:$AB$49,MATCH($B11,SOMFP!$B$11:$B$44,0),MATCH($I$8,SOMFP!$E$8:$AA$8,0)),"")
B12: =SOMFP!B12 -> Property and equipement | E12: =IFERROR(INDEX(SOMFP!$E$11:$AB$49,MATCH($B12,SOMFP!$B$11:$B$44,0),MATCH($E$8,SOMFP!$E$8:$AA$8,0)),"") -> 0 | F12: =IFERROR(INDEX(SOMFP!$E$11:$AB$49,MATCH($B12,SOMFP!$B$11:$B$44,0),MATCH($E$8,SOMFP!$E$8:$AA$8,0)),"") -> 0 | H12: =IFERROR(INDEX(SOMFP!$E$11:$AB$49,MATCH($B12,SOMFP!$B$11:$B$44,0),MATCH($H$8,SOMFP!$E$8:$AA$8,0)),"") -> 0 | I12: =IFERROR(INDEX(SOMFP!$E$11:$AB$49,MATCH($B12,SOMFP!$B$11:$B$44,0),MATCH($I$8,SOMFP!$E$8:$AA$8,0)),"") -> 0
E13: =IFERROR(INDEX(SOMFP!$E13:$AB$49,MATCH($B$11,SOMFP!$B$11:$B$44,0),MATCH($E$8,SOMFP!$E$8:$AA$8,0)),"") | F13: =IFERROR(INDEX(SOMFP!$E13:$AB$49,MATCH($B$11,SOMFP!$B$11:$B$44,0),MATCH($E$8,SOMFP!$E$8:$AA$8,0)),"") | H13: =IFERROR(INDEX(SOMFP!$E$11:$AB$49,MATCH($B13,SOMFP!$B$11:$B$44,0),MATCH($H$8,SOMFP!$E$8:$AA$8,0)),"") | I13: =IFERROR(INDEX(SOMFP!$E$11:$AB$49,MATCH($B13,SOMFP!$B$11:$B$44,0),MATCH($I$8,SOMFP!$E$8:$AA$8,0)),"")
A15: Current Assets | E15: =SUM(E16:E25) -> 0 | F15: =SUM(F16:F25) -> 0 | H15: =SUM(H16:H25) -> 0 | I15: =SUM(I16:I25) -> 0
B16: ADIB | E16: =IFERROR(INDEX(SOMFP!$E$11:$AB$49,MATCH($B16,SOMFP!$B$11:$B$44,0),MATCH($E$8,SOMFP!$E$8:$AA$8,0)),"") | F16: =IFERROR(INDEX(SOMFP!$E$11:$AB$49,MATCH($B16,SOMFP!$B$11:$B$44,0),MATCH($E$8,SOMFP!$E$8:$AA$8,0)),"") | H16: =IFERROR(INDEX(SOMFP!$E$11:$AB$49,MATCH($B16,SOMFP!$B$11:$B$44,0),MATCH($H$8,SOMFP!$E$8:$AA$8,0)),"") | I16: =IFERROR(INDEX(SOMFP!$E$11:$AB$49,MATCH($B16,SOMFP!$B$11:$B$44,0),MATCH($I$8,SOMFP!$E$8:$AA$8,0)),"")
B17: Ajman Petty-Cash | E17: =IFERROR(INDEX(SOMFP!$E$11:$AB$49,MATCH($B17,SOMFP!$B$11:$B$44,0),MATCH($E$8,SOMFP!$E$8:$AA$8,0)),"") | F17: =IFERROR(INDEX(SOMFP!$E$11:$AB$49,MATCH($B17,SOMFP!$B$11:$B$44,0),MATCH($E$8,SOMFP!$E$8:$AA$8,0)),"") | H17: =IFERROR(INDEX(SOMFP!$E$11:$AB$49,MATCH($B17,SOMFP!$B$11:$B$44,0),MATCH($H$8,SOMFP!$E$8:$AA$8,0)),"") | I17: =IFERROR(INDEX(SOMFP!$E$11:$AB$49,MATCH($B17,SOMFP!$B$11:$B$44,0),MATCH($I$8,SOMFP!$E$8:$AA$8,0)),"")
B18: Main Cash (Collection) | E18: =IFERROR(INDEX(SOMFP!$E$11:$AB$49,MATCH($B18,SOMFP!$B$11:$B$44,0),MATCH($E$8,SOMFP!$E$8:$AA$8,0)),"") | F18: =IFERROR(INDEX(SOMFP!$E$11:$AB$49,MATCH($B18,SOMFP!$B$11:$B$44,0),MATCH($E$8,SOMFP!$E$8:$AA$8,0)),"") | H18: =IFERROR(INDEX(SOMFP!$E$11:$AB$49,MATCH($B18,SOMFP!$B$11:$B$44,0),MATCH($H$8,SOMFP!$E$8:$AA$8,0)),"")
B19: Advance to employee | E19: =IFERROR(INDEX(SOMFP!$E$11:$AB$49,MATCH($B19,SOMFP!$B$11:$B$44,0),MATCH($E$8,SOMFP!$E$8:$AA$8,0)),"") | F19: =IFERROR(INDEX(SOMFP!$E$11:$AB$49,MATCH($B19,SOMFP!$B$11:$B$44,0),MATCH($E$8,SOMFP!$E$8:$AA$8,0)),"") | H19: =IFERROR(INDEX(SOMFP!$E$11:$AB$49,MATCH($B19,SOMFP!$B$11:$B$44,0),MATCH($H$8,SOMFP!$E$8:$AA$8,0)),"")
B20: Cash in Machines | E20: =IFERROR(INDEX(SOMFP!$E$11:$AB$49,MATCH($B20,SOMFP!$B$11:$B$44,0),MATCH($E$8,SOMFP!$E$8:$AA$8,0)),"") | F20: =IFERROR(INDEX(SOMFP!$E$11:$AB$49,MATCH($B20,SOMFP!$B$11:$B$44,0),MATCH($E$8,SOMFP!$E$8:$AA$8,0)),"") | H20: =IFERROR(INDEX(SOMFP!$E$11:$AB$49,MATCH($B20,SOMFP!$B$11:$B$44,0),MATCH($H$8,SOMFP!$E$8:$AA$8,0)),"") | I20: =IFERROR(INDEX(SOMFP!$E$11:$AB$49,MATCH($B20,SOMFP!$B$11:$B$44,0),MATCH($I$8,SOMFP!$E$8:$AA$8,0)),"")
B21: Fuel Adnoc balance | E21: =IFERROR(INDEX(SOMFP!$E$11:$AB$49,MATCH($B21,SOMFP!$B$11:$B$44,0),MATCH($E$8,SOMFP!$E$8:$AA$8,0)),"") | F21: =IFERROR(INDEX(SOMFP!$E$11:$AB$49,MATCH($B21,SOMFP!$B$11:$B$44,0),MATCH($E$8,SOMFP!$E$8:$AA$8,0)),"") | H21: =IFERROR(INDEX(SOMFP!$E$11:$AB$49,MATCH($B21,SOMFP!$B$11:$B$44,0),MATCH($H$8,SOMFP!$E$8:$AA$8,0)),"")
B22: Inventory | E22: =IFERROR(INDEX(SOMFP!$E$11:$AB$49,MATCH($B22,SOMFP!$B$11:$B$44,0),MATCH($E$8,SOMFP!$E$8:$AA$8,0)),"") | F22: =IFERROR(INDEX(SOMFP!$E$11:$AB$49,MATCH($B22,SOMFP!$B$11:$B$44,0),MATCH($E$8,SOMFP!$E$8:$AA$8,0)),"") | H22: =IFERROR(INDEX(SOMFP!$E$11:$AB$49,MATCH($B22,SOMFP!$B$11:$B$44,0),MATCH($H$8,SOMFP!$E$8:$AA$8,0)),"")
B23: Prepayments | E23: =IFERROR(INDEX(SOMFP!$E$11:$AB$49,MATCH($B23,SOMFP!$B$11:$B$44,0),MATCH($E$8,SOMFP!$E$8:$AA$8,0)),"") | F23: =IFERROR(INDEX(SOMFP!$E$11:$AB$49,MATCH($B23,SOMFP!$B$11:$B$44,0),MATCH($E$8,SOMFP!$E$8:$AA$8,0)),"") | H23: =IFERROR(INDEX(SOMFP!$E$11:$AB$49,MATCH($B23,SOMFP!$B$11:$B$44,0),MATCH($H$8,SOMFP!$E$8:$AA$8,0)),"") | I23: =IFERROR(INDEX(SOMFP!$E$11:$AB$49,MATCH($B23,SOMFP!$B$11:$B$44,0),MATCH($I$8,SOMFP!$E$8:$AA$8,0)),"")
B24: Accounts receivable | E24: =IFERROR(INDEX(SOMFP!$E$11:$AB$49,MATCH($B24,SOMFP!$B$11:$B$44,0),MATCH($E$8,SOMFP!$E$8:$AA$8,0)),"") | F24: =IFERROR(INDEX(SOMFP!$E$11:$AB$49,MATCH($B24,SOMFP!$B$11:$B$44,0),MATCH($E$8,SOMFP!$E$8:$AA$8,0)),"") | H24: =IFERROR(INDEX(SOMFP!$E$11:$AB$49,MATCH($B24,SOMFP!$B$11:$B$44,0),MATCH($H$8,SOMFP!$E$8:$AA$8,0)),"") | I24: =IFERROR(INDEX(SOMFP!$E$11:$AB$49,MATCH($B24,SOMFP!$B$11:$B$44,0),MATCH($I$8,SOMFP!$E$8:$AA$8,0)),"")
B25: Securities | E25: =IFERROR(INDEX(SOMFP!$E$11:$AB$49,MATCH($B25,SOMFP!$B$11:$B$44,0),MATCH($E$8,SOMFP!$E$8:$AA$8,0)),"") | F25: =IFERROR(INDEX(SOMFP!$E$11:$AB$49,MATCH($B25,SOMFP!$B$11:$B$44,0),MATCH($E$8,SOMFP!$E$8:$AA$8,0)),"") | H25: =IFERROR(INDEX(SOMFP!$E$11:$AB$49,MATCH($B25,SOMFP!$B$11:$B$44,0),MATCH($H$8,SOMFP!$E$8:$AA$8,0)),"") | I25: =IFERROR(INDEX(SOMFP!$E$11:$AB$49,MATCH($B25,SOMFP!$B$11:$B$44,0),MATCH($I$8,SOMFP!$E$8:$AA$8,0)),"")
A27: Total Assets | E27: =+E10+E15 -> 0 | F27: =+F10+F15 -> 0 | H27: =+H10+H15 -> 0 | I27: =+I10+#REF!+I15 -> #REF!
A29: Equity & Liabilities:
A30: Equity | E30: =SUM(E31:E35) -> -16699.073 | F30: =SUM(F31:F35) -> -16699.073 | H30: =SUM(H31:H35) -> 0 | I30: =SUM(I31:I35) -> 0
B31: =SOMFP!B30 -> Net Income | E31: =IFERROR(INDEX(SOMFP!$E$11:$AB$49,MATCH($B31,SOMFP!$B$11:$B$44,0),MATCH($E$8,SOMFP!$E$8:$AA$8,0)),"") -> 0 | F31: =IFERROR(INDEX(SOMFP!$E$11:$AB$49,MATCH($B31,SOMFP!$B$11:$B$44,0),MATCH($E$8,SOMFP!$E$8:$AA$8,0)),"") -> 0 | H31: =IFERROR(INDEX(SOMFP!$E$11:$AB$49,MATCH($B31,SOMFP!$B$11:$B$44,0),MATCH($H$8,SOMFP!$E$8:$AA$8,0)),"") -> 0 | I31: =IFERROR(INDEX(SOMFP!$E$11:$AB$49,MATCH($B31,SOMFP!$B$11:$B$44,0),MATCH($I$8,SOMFP!$E$8:$AA$8,0)),"") -> 0
B32: =SOMFP!B31 -> Drawings | E32: =IFERROR(INDEX(SOMFP!$E$11:$AB$49,MATCH($B32,SOMFP!$B$11:$B$44,0),MATCH($E$8,SOMFP!$E$8:$AA$8,0)),"") -> 0 | F32: =IFERROR(INDEX(SOMFP!$E$11:$AB$49,MATCH($B32,SOMFP!$B$11:$B$44,0),MATCH($E$8,SOMFP!$E$8:$AA$8,0)),"") -> 0 | H32: =IFERROR(INDEX(SOMFP!$E$11:$AB$49,MATCH($B32,SOMFP!$B$11:$B$44,0),MATCH($H$8,SOMFP!$E$8:$AA$8,0)),"") -> 0 | I32: =IFERROR(INDEX(SOMFP!$E$11:$AB$49,MATCH($B32,SOMFP!$B$11:$B$44,0),MATCH($I$8,SOMFP!$E$8:$AA$8,0)),"") -> 0
B33: =SOMFP!B32 -> Opening Balance Equity | E33: =IFERROR(INDEX(SOMFP!$E$11:$AB$49,MATCH($B33,SOMFP!$B$11:$B$44,0),MATCH($E$8,SOMFP!$E$8:$AA$8,0)),"") -> 0 | F33: =IFERROR(INDEX(SOMFP!$E$11:$AB$49,MATCH($B33,SOMFP!$B$11:$B$44,0),MATCH($E$8,SOMFP!$E$8:$AA$8,0)),"") -> 0 | H33: =IFERROR(INDEX(SOMFP!$E$11:$AB$49,MATCH($B33,SOMFP!$B$11:$B$44,0),MATCH($H$8,SOMFP!$E$8:$AA$8,0)),"") -> 0 | I33: =IFERROR(INDEX(SOMFP!$E$11:$AB$49,MATCH($B33,SOMFP!$B$11:$B$44,0),MATCH($I$8,SOMFP!$E$8:$AA$8,0)),"") -> 0
B34: =SOMFP!B33 -> Retained Earnings | E34: =IFERROR(INDEX(SOMFP!$E$11:$AB$49,MATCH($B34,SOMFP!$B$11:$B$44,0),MATCH($E$8,SOMFP!$E$8:$AA$8,0)),"") -> -16699.073 | F34: =IFERROR(INDEX(SOMFP!$E$11:$AB$49,MATCH($B34,SOMFP!$B$11:$B$44,0),MATCH($E$8,SOMFP!$E$8:$AA$8,0)),"") -> -16699.073 | H34: =IFERROR(INDEX(SOMFP!$E$11:$AB$49,MATCH($B34,SOMFP!$B$11:$B$44,0),MATCH($H$8,SOMFP!$E$8:$AA$8,0)),"") -> 0 | I34: =IFERROR(INDEX(SOMFP!$E$11:$AB$49,MATCH($B34,SOMFP!$B$11:$B$44,0),MATCH($I$8,SOMFP!$E$8:$AA$8,0)),"") -> 0
B35: =SOMFP!B34 -> Share holder current account | E35: =IFERROR(INDEX(SOMFP!$E$11:$AB$49,MATCH($B35,SOMFP!$B$11:$B$44,0),MATCH($E$8,SOMFP!$E$8:$AA$8,0)),"") -> 0 | F35: =IFERROR(INDEX(SOMFP!$E$11:$AB$49,MATCH($B35,SOMFP!$B$11:$B$44,0),MATCH($E$8,SOMFP!$E$8:$AA$8,0)),"") -> 0 | H35: =IFERROR(INDEX(SOMFP!$E$11:$AB$49,MATCH($B35,SOMFP!$B$11:$B$44,0),MATCH($H$8,SOMFP!$E$8:$AA$8,0)),"") -> 0 | I35: =IFERROR(INDEX(SOMFP!$E$11:$AB$49,MATCH($B35,SOMFP!$B$11:$B$44,0),MATCH($I$8,SOMFP!$E$8:$AA$8,0)),"") -> 0
A37: Non-current Liabilities | E37: =SUM(E38:E39) -> 0 | F37: =SUM(F38:F39) -> 0 | H37: =SUM(H38:H39) -> 0 | I37: =SUM(I38:I39) -> 0
E38: =IFERROR(INDEX(SOMFP!$E$11:$AB$49,MATCH($B38,SOMFP!$B$11:$B$44,0),MATCH($E$8,SOMFP!$E$8:$AA$8,0)),"") | F38: =IFERROR(INDEX(SOMFP!$E$11:$AB$49,MATCH($B38,SOMFP!$B$11:$B$44,0),MATCH($E$8,SOMFP!$E$8:$AA$8,0)),"") | H38: =IFERROR(INDEX(SOMFP!$E$11:$AB$49,MATCH($B38,SOMFP!$B$11:$B$44,0),MATCH($H$8,SOMFP!$E$8:$AA$8,0)),"") | I38: =IFERROR(INDEX(SOMFP!$E$11:$AB$49,MATCH($B38,SOMFP!$B$11:$B$44,0),MATCH($I$8,SOMFP!$E$8:$AA$8,0)),"")
B39: =SOMFP!B38 -> Investment from associates | E39: =IFERROR(INDEX(SOMFP!$E$11:$AB$49,MATCH($B39,SOMFP!$B$11:$B$44,0),MATCH($E$8,SOMFP!$E$8:$AA$8,0)),"") -> 0 | F39: =IFERROR(INDEX(SOMFP!$E$11:$AB$49,MATCH($B39,SOMFP!$B$11:$B$44,0),MATCH($E$8,SOMFP!$E$8:$AA$8,0)),"") -> 0 | H39: =IFERROR(INDEX(SOMFP!$E$11:$AB$49,MATCH($B39,SOMFP!$B$11:$B$44,0),MATCH($H$8,SOMFP!$E$8:$AA$8,0)),"") -> 0 | I39: =IFERROR(INDEX(SOMFP!$E$11:$AB$49,MATCH($B39,SOMFP!$B$11:$B$44,0),MATCH($I$8,SOMFP!$E$8:$AA$8,0)),"") -> 0
A41: Current Liabilities | E41: =SUM(E42:E48) -> 0 | F41: =SUM(F42:F48) -> 0 | H41: =SUM(H42:H48) -> 0 | I41: =SUM(I42:I48) -> 0
B42: =SOMFP!B41 -> Accounts Payable (A/P) | E42: =IFERROR(INDEX(SOMFP!$E$11:$AB$49,MATCH($B42,SOMFP!$B$11:$B$44,0),MATCH($E$8,SOMFP!$E$8:$AA$8,0)),"") -> 0 | F42: =IFERROR(INDEX(SOMFP!$E$11:$AB$49,MATCH($B42,SOMFP!$B$11:$B$44,0),MATCH($E$8,SOMFP!$E$8:$AA$8,0)),"") -> 0 | H42: =IFERROR(INDEX(SOMFP!$E$11:$AB$49,MATCH($B42,SOMFP!$B$11:$B$44,0),MATCH($H$8,SOMFP!$E$8:$AA$8,0)),"") -> 0 | I42: =IFERROR(INDEX(SOMFP!$E$11:$AB$49,MATCH($B42,SOMFP!$B$11:$B$44,0),MATCH($I$8,SOMFP!$E$8:$AA$8,0)),"") -> 0
B43: =SOMFP!B42 -> Machine Rent Payable | E43: =IFERROR(INDEX(SOMFP!$E$11:$AB$49,MATCH($B43,SOMFP!$B$11:$B$44,0),MATCH($E$8,SOMFP!$E$8:$AA$8,0)),"") -> 0 | F43: =IFERROR(INDEX(SOMFP!$E$11:$AB$49,MATCH($B43,SOMFP!$B$11:$B$44,0),MATCH($E$8,SOMFP!$E$8:$AA$8,0)),"") -> 0 | H43: =IFERROR(INDEX(SOMFP!$E$11:$AB$49,MATCH($B43,SOMFP!$B$11:$B$44,0),MATCH($H$8,SOMFP!$E$8:$AA$8,0)),"") -> 0 | I43: =IFERROR(INDEX(SOMFP!$E$11:$AB$49,MATCH($B43,SOMFP!$B$11:$B$44,0),MATCH($I$8,SOMFP!$E$8:$AA$8,0)),"") -> 0
B44: =SOMFP!B43 -> Loan from Infusion | E44: =IFERROR(INDEX(SOMFP!$E$11:$AB$49,MATCH($B44,SOMFP!$B$11:$B$44,0),MATCH($E$8,SOMFP!$E$8:$AA$8,0)),"") -> 0 | F44: =IFERROR(INDEX(SOMFP!$E$11:$AB$49,MATCH($B44,SOMFP!$B$11:$B$44,0),MATCH($E$8,SOMFP!$E$8:$AA$8,0)),"") -> 0 | H44: =IFERROR(INDEX(SOMFP!$E$11:$AB$49,MATCH($B44,SOMFP!$B$11:$B$44,0),MATCH($H$8,SOMFP!$E$8:$AA$8,0)),"") -> 0 | I44: =IFERROR(INDEX(SOMFP!$E$11:$AB$49,MATCH($B44,SOMFP!$B$11:$B$44,0),MATCH($I$8,SOMFP!$E$8:$AA$8,0)),"") -> 0
B45: =SOMFP!B44 -> Loan From Mr saeed | E45: =IFERROR(INDEX(SOMFP!$E$11:$AB$60,MATCH($B45,SOMFP!$B$11:$B$60,0),MATCH($E$8,SOMFP!$E$8:$AA$8,0)),"") -> 0 | F45: =IFERROR(INDEX(SOMFP!$E$11:$AB$60,MATCH($B45,SOMFP!$B$11:$B$60,0),MATCH($E$8,SOMFP!$E$8:$AA$8,0)),"") -> 0 | H45: =IFERROR(INDEX(SOMFP!$E$11:$AB$60,MATCH($B45,SOMFP!$B$11:$B$60,0),MATCH($H$8,SOMFP!$E$8:$AA$8,0)),"") -> 0 | I45: =IFERROR(INDEX(SOMFP!$E$11:$AB$49,MATCH($B45,SOMFP!$B$11:$B$44,0),MATCH($I$8,SOMFP!$E$8:$AA$8,0)),"") -> 0
B46: =SOMFP!B45 -> Salaries & wages payable | E46: =IFERROR(INDEX(SOMFP!$E$11:$AB$60,MATCH($B46,SOMFP!$B$11:$B$60,0),MATCH($E$8,SOMFP!$E$8:$AA$8,0)),"") -> 0 | F46: =IFERROR(INDEX(SOMFP!$E$11:$AB$60,MATCH($B46,SOMFP!$B$11:$B$60,0),MATCH($E$8,SOMFP!$E$8:$AA$8,0)),"") -> 0 | H46: =IFERROR(INDEX(SOMFP!$E$11:$AB$60,MATCH($B46,SOMFP!$B$11:$B$60,0),MATCH($H$8,SOMFP!$E$8:$AA$8,0)),"") -> 0
B47: =SOMFP!B46 -> Transguard Payable | E47: =IFERROR(INDEX(SOMFP!$E$11:$AB$60,MATCH($B47,SOMFP!$B$11:$B$60,0),MATCH($E$8,SOMFP!$E$8:$AA$8,0)),"") -> 0 | F47: =IFERROR(INDEX(SOMFP!$E$11:$AB$60,MATCH($B47,SOMFP!$B$11:$B$60,0),MATCH($E$8,SOMFP!$E$8:$AA$8,0)),"") -> 0 | H47: =IFERROR(INDEX(SOMFP!$E$11:$AB$60,MATCH($B47,SOMFP!$B$11:$B$60,0),MATCH($H$8,SOMFP!$E$8:$AA$8,0)),"") -> 0
B48: =SOMFP!B47 -> Other Payables | E48: =IFERROR(INDEX(SOMFP!$E$11:$AB$60,MATCH($B48,SOMFP!$B$11:$B$60,0),MATCH($E$8,SOMFP!$E$8:$AA$8,0)),"") -> 0 | F48: =IFERROR(INDEX(SOMFP!$E$11:$AB$60,MATCH($B48,SOMFP!$B$11:$B$60,0),MATCH($E$8,SOMFP!$E$8:$AA$8,0)),"") -> 0 | H48: =IFERROR(INDEX(SOMFP!$E$11:$AB$60,MATCH($B48,SOMFP!$B$11:$B$60,0),MATCH($H$8,SOMFP!$E$8:$AA$8,0)),"") -> 0 | I48: =IFERROR(INDEX(SOMFP!$E$11:$AB$49,MATCH($B48,SOMFP!$B$11:$B$44,0),MATCH($I$8,SOMFP!$E$8:$AA$8,0)),"")
E49: =IFERROR(INDEX(SOMFP!$E$11:$AB$60,MATCH($B49,SOMFP!$B$11:$B$60,0),MATCH($E$8,SOMFP!$E$8:$AA$8,0)),"") | F49: =IFERROR(INDEX(SOMFP!$E$11:$AB$60,MATCH($B49,SOMFP!$B$11:$B$60,0),MATCH($E$8,SOMFP!$E$8:$AA$8,0)),"") | H49: =IFERROR(INDEX(SOMFP!$E$11:$AB$60,MATCH($B49,SOMFP!$B$11:$B$60,0),MATCH($H$8,SOMFP!$E$8:$AA$8,0)),"")
A50: Total Equity & Liabilities | E50: =+E30+E37+E41 -> -16699.073 | F50: =+F30+F37+F41 -> -16699.073 | H50: =+H30+H37+H41 -> 0 | I50: =+I30+I37+I41 -> 0

Sheet SOMFP
A2: =Cover!A9 -> Afrodiva Exotic Hair Boutique Ltd.
A3: =Cover!A10 -> DUABI UAE
A5: STATEMENT OF FINANCIAL POSITION
A6: ="For The Period " -> For The Period
A7: Amount in AED
A8: Particulars | C8: Note | E8: =+SOMCI!F9 -> 45689 | G8: =DATE(YEAR(E8),MONTH(E8)+1,1) -> 45717 | I8: =DATE(YEAR(G8),MONTH(G8)+1,1) -> 45748 | K8: =DATE(YEAR(I8),MONTH(I8)+1,1) -> 45778 | M8: =DATE(YEAR(K8),MONTH(K8)+1,1) -> 45809 | O8: =DATE(YEAR(M8),MONTH(M8)+1,1) -> 45839 | Q8: =DATE(YEAR(O8),MONTH(O8)+1,1) -> 45870 | S8: =DATE(YEAR(Q8),MONTH(Q8)+1,1) -> 45901 | U8: =DATE(YEAR(S8),MONTH(S8)+1,1) -> 45931 | W8: =DATE(YEAR(U8),MONTH(U8)+1,1) -> 45962 | Y8: =DATE(YEAR(W8),MONTH(W8)+1,1) -> 45992 | AA8: =DATE(YEAR(Y8),MONTH(Y8)+1,1) -> 46023
A9: Assets: | E9: DIFC | F9: Al Barsha | G9: DIFC | H9: Al Barsha | I9: DIFC | J9: Al Barsha | K9: DIFC | L9: Al Barsha | M9: DIFC | N9: Al Barsha | O9: DIFC | P9: Al Barsha | Q9: DIFC | R9: Al Barsha | S9: DIFC | T9: Al Barsha | U9: DIFC | V9: Al Barsha | W9: DIFC | X9: Al Barsha | Y9: DIFC | Z9: Al Barsha | AA9: DIFC | AB9: Al Barsha
A10: Fixed Assets | E10: =SUM(E11:E13) -> 0 | G10: =SUM(G11:G13) -> 0 | I10: =SUM(I11:I13) -> 0 | K10: =SUM(K11:K13) -> 0 | M10: =SUM(M11:M13) -> 0 | O10: =SUM(O11:O13) -> 0 | Q10: =SUM(Q11:Q13) -> 0 | S10: =SUM(S11:S13) -> 0 | U10: =SUM(U11:U13) -> 0 | W10: =SUM(W11:W13) -> 0 | Y10: =SUM(Y11:Y13) -> 0 | AB10: =SUM(AB11:AB13) -> 0
AA11: =SUMIF('Linked BS'!$A$7:$A$46,SOMFP!A11,'Linked BS'!$C$7:$C$46) -> 0 | AB11: =SUMIF('Linked BS'!$A$7:$A$46,SOMFP!B11,'Linked BS'!$C$7:$C$46) -> 0
B12: Property and equipement | AA12: =SUMIF('Linked BS'!$A$7:$A$46,SOMFP!A12,'Linked BS'!$C$7:$C$46) -> 0 | AB12: =SUMIF('Linked BS'!$A$7:$A$46,SOMFP!B12,'Linked BS'!$C$7:$C$46) -> 0
AA13: =SUMIF('Linked BS'!$A$7:$A$46,SOMFP!A13,'Linked BS'!$C$7:$C$46) -> 0 | AB13: =SUMIF('Linked BS'!$A$7:$A$46,SOMFP!B13,'Linked BS'!$C$7:$C$46) -> 0
A15: Current Assets | E15: =SUM(E16:E25) -> 0 | G15: =SUM(G16:G25) -> 0 | I15: =SUM(I16:I25) -> 0 | K15: =SUM(K16:K25) -> 0 | M15: =SUM(M16:M25) -> 0 | O15: =SUM(O16:O25) -> 0 | Q15: =SUM(Q16:Q25) -> 0 | S15: =SUM(S16:S25) -> 0 | U15: =SUM(U16:U25) -> 0 | W15: =SUM(W16:W25) -> 0 | Y15: =SUM(Y16:Y25) -> 0 | AB15: =SUM(AB16:AB25) -> 0
B16: Trade & other receivables | AA16: =SUMIF('Linked BS'!$B$7:$B$46,B16,'Linked BS'!$C$7:$C$46) -> 0 | AB16: =SUMIF('Linked BS'!$A$7:$A$46,SOMFP!B16,'Linked BS'!$C$7:$C$46) -> 0
B17: Inventory | AA17: =SUMIF('Linked BS'!$B$7:$B$46,B17,'Linked BS'!$C$7:$C$46) -> 108489 | AB17: =SUMIF('Linked BS'!$A$7:$A$46,SOMFP!B17,'Linked BS'!$C$7:$C$46) -> 0
B18: Security Deposit | AA18: =SUMIF('Linked BS'!$B$7:$B$46,B18,'Linked BS'!$C$7:$C$46) -> 0 | AB18: =SUMIF('Linked BS'!$A$7:$A$46,SOMFP!B18,'Linked BS'!$C$7:$C$46) -> 0
B19: Employee Advances | AA19: =SUMIF('Linked BS'!$B$7:$B$46,B19,'Linked BS'!$C$7:$C$46) -> 0 | AB19: =SUMIF('Linked BS'!$A$7:$A$46,SOMFP!B19,'Linked BS'!$C$7:$C$46) -> 0
B20: Prepayments & Prepaid Expenses | AA20: =SUMIF('Linked BS'!$B$7:$B$46,B20,'Linked BS'!$C$7:$C$46) -> 15583.33 | AB20: =SUMIF('Linked BS'!$A$7:$A$46,SOMFP!B20,'Linked BS'!$C$7:$C$46) -> 0
B21: Cash and cash equivalents | AA21: =SUMIF('Linked BS'!$B$7:$B$46,B21,'Linked BS'!$C$7:$C$46) -> 0 | AB21: =SUMIF('Linked BS'!$A$7:$A$46,SOMFP!B21,'Linked BS'!$C$7:$C$46) -> 0
B22: Cash In Hand Vanissa | AA22: =SUMIF('Linked BS'!$B$7:$B$46,B22,'Linked BS'!$C$7:$C$46) -> 0 | AB22: =SUMIF('Linked BS'!$A$7:$A$46,SOMFP!B22,'Linked BS'!$C$7:$C$46) -> 0
B23: Cash In Hand Omotola | AA23: =SUMIF('Linked BS'!$B$7:$B$46,B23,'Linked BS'!$C$7:$C$46) -> 0 | AB23: =SUMIF('Linked BS'!$A$7:$A$46,SOMFP!B23,'Linked BS'!$C$7:$C$46) -> 0
B24: Bank | AA24: =SUMIF('Linked BS'!$B$7:$B$46,B24,'Linked BS'!$C$7:$C$46) -> 69576 | AB24: =SUMIF('Linked BS'!$A$7:$A$46,SOMFP!B24,'Linked BS'!$C$7:$C$46) -> 0
B25: InPut VAT | AA25: =SUMIF('Linked BS'!$B$7:$B$46,B25,'Linked BS'!$C$7:$C$46) -> 0 | AB25: =SUMIF('Linked BS'!$A$7:$A$46,SOMFP!B25,'Linked BS'!$C$7:$C$46) -> 0
A27: Total Assets | E27: =+E10+E15 -> 0 | G27: =+G10+G15 -> 0 | I27: =+I10+I15 -> 0 | K27: =+K10+K15 -> 0 | M27: =+M10+M15 -> 0 | O27: =+O10+O15 -> 0 | Q27: =+Q10+Q15 -> 0 | S27: =+S10+S15 -> 0 | U27: =+U10+U15 -> 0 | W27: =+W10+W15 -> 0 | Y27: =+Y10+Y15 -> 0 | AB27: =+AB10+AB15 -> 0
A28: Equity & Liabilities:
A29: Equity | E29: =SUM(E30:E34) -> 0 | G29: =SUM(G30:G34) -> 0 | I29: =SUM(I30:I34) -> 0 | K29: =SUM(K30:K34) -> 0 | M29: =SUM(M30:M34) -> 0 | O29: =SUM(O30:O34) -> 0 | Q29: =SUM(Q30:Q34) -> 0 | S29: =SUM(S30:S34) -> 0 | U29: =SUM(U30:U34) -> 0 | W29: =SUM(W30:W34) -> 0 | Y29: =SUM(Y30:Y34) -> 0 | AB29: =SUM(AB30:AB34) -> 0
B30: Net Income | AA30: =SUMIF('Linked BS'!$A$7:$A$46,SOMFP!A30,'Linked BS'!$C$7:$C$46) -> 0 | AB30: =SUMIF('Linked BS'!$A$7:$A$46,SOMFP!B30,'Linked BS'!$C$7:$C$46) -> 0
B31: Drawings | AA31: =SUMIF('Linked BS'!$A$7:$A$46,SOMFP!A31,'Linked BS'!$C$7:$C$46) -> 0 | AB31: =SUMIF('Linked BS'!$A$7:$A$46,SOMFP!B31,'Linked BS'!$C$7:$C$46) -> 0
B32: Opening Balance Equity | AA32: =SUMIF('Linked BS'!$A$7:$A$46,SOMFP!A32,'Linked BS'!$C$7:$C$46) -> 0 | AB32: =SUMIF('Linked BS'!$A$7:$A$46,SOMFP!B32,'Linked BS'!$C$7:$C$46) -> 0
B33: Retained Earnings | AA33: =SOMCI!AB49 -> -16699.073 | AB33: =SOMCI!AC49 -> 0
B34: Share holder current account
A36: Non-current Liabilities | E36: =SUM(E37:E38) -> 0 | G36: =SUM(G37:G38) -> 0 | I36: =SUM(I37:I38) -> 0 | K36: =SUM(K37:K38) -> 0 | M36: =SUM(M37:M38) -> 0 | O36: =SUM(O37:O38) -> 0 | Q36: =SUM(Q37:Q38) -> 0 | S36: =SUM(S37:S38) -> 0 | U36: =SUM(U37:U38) -> 0 | W36: =SUM(W37:W38) -> 0 | Y36: =SUM(Y37:Y38) -> 0 | AB36: =SUM(AB37:AB38) -> 0
AA37: =SUMIF('Linked BS'!$A$7:$A$46,SOMFP!A37,'Linked BS'!$C$7:$C$46) -> 0 | AB37: =SUMIF('Linked BS'!$A$7:$A$46,SOMFP!B37,'Linked BS'!$C$7:$C$46) -> 0
B38: Investment from associates | AA38: =SUMIF('Linked BS'!$A$7:$A$46,SOMFP!A38,'Linked BS'!$C$7:$C$46) -> 0 | AB38: =SUMIF('Linked BS'!$A$7:$A$46,SOMFP!B38,'Linked BS'!$C$7:$C$46) -> 0
A40: Current Liabilities | E40: =SUM(E41:E47) -> 0 | G40: =SUM(G41:G47) -> 0 | I40: =SUM(I41:I47) -> 0 | K40: =SUM(K41:K47) -> 0 | M40: =SUM(M41:M47) -> 0 | O40: =SUM(O41:O47) -> 0 | Q40: =SUM(Q41:Q47) -> 0 | S40: =SUM(S41:S47) -> 0 | U40: =SUM(U41:U47) -> 0 | W40: =SUM(W41:W47) -> 0 | Y40: =SUM(Y41:Y47) -> 0 | AB40: =SUM(AB41:AB47) -> 0
B41: Accounts Payable (A/P) | AA41: =SUMIF('Linked BS'!$A$7:$A$46,SOMFP!A41,'Linked BS'!$C$7:$C$46) -> 0 | AB41: =SUMIF('Linked BS'!$A$7:$A$46,SOMFP!B41,'Linked BS'!$C$7:$C$46) -> 0
B42: Machine Rent Payable | AA42: =SUMIF('Linked BS'!$A$7:$A$46,SOMFP!A42,'Linked BS'!$C$7:$C$46) -> 0 | AB42: =SUMIF('Linked BS'!$A$7:$A$46,SOMFP!B42,'Linked BS'!$C$7:$C$46) -> 0
B43: Loan from Infusion | AA43: =SUMIF('Linked BS'!$A$7:$A$46,SOMFP!A43,'Linked BS'!$C$7:$C$46) -> 0 | AB43: =SUMIF('Linked BS'!$A$7:$A$46,SOMFP!B43,'Linked BS'!$C$7:$C$46) -> 0
B44: Loan From Mr saeed | AA44: =SUMIF('Linked BS'!$A$7:$A$46,SOMFP!A44,'Linked BS'!$C$7:$C$46) -> 0 | AB44: =SUMIF('Linked BS'!$A$7:$A$46,SOMFP!B44,'Linked BS'!$C$7:$C$46) -> 0
B45: Salaries & wages payable | AA45: =SUMIF('Linked BS'!$A$7:$A$46,SOMFP!A45,'Linked BS'!$C$7:$C$46) -> 0 | AB45: =SUMIF('Linked BS'!$A$7:$A$46,SOMFP!B45,'Linked BS'!$C$7:$C$46) -> 0
B46: Transguard Payable | AA46: =SUMIF('Linked BS'!$A$7:$A$46,SOMFP!A46,'Linked BS'!$C$7:$C$46) -> 0 | AB46: =SUMIF('Linked BS'!$A$7:$A$46,SOMFP!B46,'Linked BS'!$C$7:$C$46) -> 0
B47: Other Payables | AA47: =SUMIF('Linked BS'!$A$7:$A$46,SOMFP!A47,'Linked BS'!$C$7:$C$46) -> 0 | AB47: =SUMIF('Linked BS'!$A$7:$A$46,SOMFP!B47,'Linked BS'!$C$7:$C$46) -> 0
A49: Total Equity & Liabilities | E49: =+E29+E36+E40 -> 0 | G49: =+G29+G36+G40 -> 0 | I49: =+I29+I36+I40 -> 0 | K49: =+K29+K36+K40 -> 0 | M49: =+M29+M36+M40 -> 0 | O49: =+O29+O36+O40 -> 0 | Q49: =+Q29+Q36+Q40 -> 0 | S49: =+S29+S36+S40 -> 0 | U49: =+U29+U36+U40 -> 0 | W49: =+W29+W36+W40 -> 0 | Y49: =+Y29+Y36+Y40 -> 0 | AA49: =+AA29+AA36+AA40 -> 0 | AB49: =+AB29+AB36+AB40 -> 0
A51: Error | E51: =+E27-E49 -> 0 | G51: =+G27-G49 -> 0 | I51: =+I27-I49 -> 0 | K51: =+K27-K49 -> 0 | M51: =+M27-M49 -> 0 | O51: =+O27-O49 -> 0 | Q51: =+Q27-Q49 -> 0 | S51: =+S27-S49 -> 0 | U51: =+U27-U49 -> 0 | W51: =+W27-W49 -> 0 | Y51: =+Y27-Y49 -> 0 | AA51: =+AA27-AA49 -> 0 | AB51: =+AB27-AB49 -> 0

Sheet SOCI
A2: =Cover!A9 -> Afrodiva Exotic Hair Boutique Ltd.
A3: =Cover!A10 -> DUABI UAE
A5: STATEMENT OF COMPREHENSIVE INCOME
A6: =Galance!D20 -> For the month of January - 2026
A7: Amount in AED
A8: Particulars | D8: Notes | F8: =VLOOKUP(Cover!$C$3,Cover!$G$4:$Q$15,4,) -> 46023 | I8: =DATE(YEAR(F8),MONTH(F8)-1,1) -> 45992 | K8: YTD
F9: DIFC | G9: Al Barsha
A10: Revenue | F10: =SUM(F11:F12)-F13 -> 87643.893 | G10: =SUM(G11:G12)-G13 -> 0 | I10: =SUM(I11:I12) -> 0 | K10: =SUM(K11:K13) -> 87643.893
B11: =SOMCI!B13 -> Sales | F11: =IFERROR(INDEX(SOMCI!$F$13:$AC$60,MATCH(SOCI!$B11,SOMCI!$B$13:$B$60,0),MATCH(SOCI!F$8,SOMCI!$F$9:$AC$9,0)),"") -> 87643.893 | G11: {=IFERROR(INDEX(SOMCI!$F$13:$AC$60,MATCH(SOCI!$B11,SOMCI!$B$13:$B$60,0),MATCH(0,(SOMCI!$F$9:$AC$9=SOCI!F$8)*(SOMCI!$F$10:$AC$10=SOCI!$G$9),1)),"")} -> 0 | I11: =IFERROR(INDEX(SOMCI!$F$13:$AD$50,MATCH(SOCI!$B11,SOMCI!$B$13:$B$50,0),MATCH(SOCI!I$8,SOMCI!$F$9:$AD$9,0)),"") -> 0 | K11: =SUM(F11:J11) -> 87643.893
B12: =SOMCI!B14 -> E-Commerce's/Online Sale | F12: =IFERROR(INDEX(SOMCI!$F$13:$AC$60,MATCH(SOCI!$B12,SOMCI!$B$13:$B$60,0),MATCH(SOCI!F$8,SOMCI!$F$9:$AC$9,0)),"") -> 0 | G12: {=IFERROR(INDEX(SOMCI!$F$13:$AC$60,MATCH(SOCI!$B12,SOMCI!$B$13:$B$60,0),MATCH(0,(SOMCI!$F$9:$AC$9=SOCI!F$8)*(SOMCI!$F$10:$AC$10=SOCI!$G$9),1)),"")} -> 0 | I12: =IFERROR(INDEX(SOMCI!$F$13:$AB$50,MATCH(SOCI!$B12,SOMCI!$B$13:$B$50,0),MATCH(SOCI!I$8,SOMCI!$F$9:$AB$9,0)),"") -> 0 | K12: =SUM(F12:J12) -> 0
B13: =SOMCI!B15 -> Sales Discounts | F13: =IFERROR(INDEX(SOMCI!$F$13:$AC$60,MATCH(SOCI!$B13,SOMCI!$B$13:$B$60,0),MATCH(SOCI!F$8,SOMCI!$F$9:$AC$9,0)),"") -> 0 | G13: {=IFERROR(INDEX(SOMCI!$F$13:$AC$60,MATCH(SOCI!$B13,SOMCI!$B$13:$B$60,0),MATCH(0,(SOMCI!$F$9:$AC$9=SOCI!F$8)*(SOMCI!$F$10:$AC$10=SOCI!$G$9),1)),"")} -> 0 | K13: =SUM(F13:J13) -> 0
A14: Direct Expenses | F14: =SUM(F15:F17) -> 35045.157 | G14: =SUM(G15:G17) -> 0 | H14: =SUM(H15:H17) -> 0 | I14: =SUM(I15:I17) -> 0 | J14: =SUM(J15:J17) -> 0 | K14: =SUM(K15:K17) -> 35045.157
F15: =IFERROR(INDEX(SOMCI!$F$13:$AB$50,MATCH(SOCI!$B15,SOMCI!$B$13:$B$50,0),MATCH(SOCI!F$8,SOMCI!$F$9:$AB$9,0)),"") | G15: =IFERROR(INDEX(SOMCI!$F$13:$AB$50,MATCH(SOCI!$B15,SOMCI!$B$13:$B$50,0),MATCH(SOCI!G$8,SOMCI!$F$9:$AB$9,0)),"") | I15: =IFERROR(INDEX(SOMCI!$F$13:$AB$50,MATCH(SOCI!$B15,SOMCI!$B$13:$B$50,0),MATCH(SOCI!I$8,SOMCI!$F$9:$AB$9,0)),"") | K15: =IFERROR(INDEX(SOMCI!$F$13:$AD$50,MATCH(SOCI!$B15,SOMCI!$B$13:$B$50,0),MATCH(SOCI!K$8,SOMCI!$F$9:$AD$9,0)),"")
B16: =SOMCI!B18 -> Cost of Sales | F16: =IFERROR(INDEX(SOMCI!$F$13:$AB$50,MATCH(SOCI!$B16,SOMCI!$B$13:$B$50,0),MATCH(SOCI!F$8,SOMCI!$F$9:$AB$9,0)),"") -> 35045.157 | G16: {=IFERROR(INDEX(SOMCI!$F$13:$AC$60,MATCH(SOCI!$B16,SOMCI!$B$13:$B$60,0),MATCH(0,(SOMCI!$F$9:$AC$9=SOCI!F$8)*(SOMCI!$F$10:$AC$10=SOCI!$G$9),1)),"")} -> 0 | I16: =IFERROR(INDEX(SOMCI!$F$13:$AB$50,MATCH(SOCI!$B16,SOMCI!$B$13:$B$50,0),MATCH(SOCI!I$8,SOMCI!$F$9:$AB$9,0)),"") -> 0 | K16: =SUM(F16:J16) -> 35045.157
F17: =IFERROR(INDEX(SOMCI!$F$13:$AB$50,MATCH(SOCI!$B17,SOMCI!$B$13:$B$50,0),MATCH(SOCI!F$8,SOMCI!$F$9:$AB$9,0)),"") | G17: =IFERROR(INDEX(SOMCI!$F$13:$AB$50,MATCH(SOCI!$B17,SOMCI!$B$13:$B$50,0),MATCH(SOCI!G$8,SOMCI!$F$9:$AB$9,0)),"") | I17: =IFERROR(INDEX(SOMCI!$F$13:$AB$50,MATCH(SOCI!$B17,SOMCI!$B$13:$B$50,0),MATCH(SOCI!I$8,SOMCI!$F$9:$AB$9,0)),"") | K17: =IFERROR(INDEX(SOMCI!$F$13:$AD$50,MATCH(SOCI!$B17,SOMCI!$B$13:$B$50,0),MATCH(SOCI!K$8,SOMCI!$F$9:$AD$9,0)),"")
A18: Gross Profit / (Loss) | F18: =+F10-F14 -> 52598.737 | G18: =IFERROR(INDEX(SOMCI!$F$13:$AB$50,MATCH(SOCI!$B18,SOMCI!$B$13:$B$50,0),MATCH(SOCI!G$8,SOMCI!$F$9:$AB$9,0)),"") | H18: =+H10-H14 -> 0 | I18: =+I10-I14 -> 0 | K18: =+K10-K14 -> 52598.737
A19: Indirect Expenses | G19: =IFERROR(INDEX(SOMCI!$F$13:$AB$50,MATCH(SOCI!$B19,SOMCI!$B$13:$B$50,0),MATCH(SOCI!G$8,SOMCI!$F$9:$AB$9,0)),"") | I19: =IFERROR(INDEX(SOMCI!$F$13:$AB$50,MATCH(SOCI!#REF!,SOMCI!$B$13:$B$50,0),MATCH(SOCI!I$8,SOMCI!$F$9:$AB$9,0)),"")
A20: Operating & Administrative Exp. | F20: =SUM(F21:F35) -> 6797.81 | G20: =SUM(G21:G35) -> 0 | I20: =SUM(I21:I35) -> 0 | K20: =SUM(K21:K35) -> 6797.81
B21: =SOMCI!B23 -> Salary & wages | F21: =IFERROR(INDEX(SOMCI!$F$13:$AB$50,MATCH(SOCI!$B21,SOMCI!$B$13:$B$50,0),MATCH(SOCI!F$8,SOMCI!$F$9:$AB$9,0)),"") -> 0 | G21: {=IFERROR(INDEX(SOMCI!$F$13:$AC$60,MATCH(SOCI!$B21,SOMCI!$B$13:$B$60,0),MATCH(0,(SOMCI!$F$9:$AC$9=SOCI!F$8)*(SOMCI!$F$10:$AC$10=SOCI!$G$9),1)),"")} -> 0 | I21: =IFERROR(INDEX(SOMCI!$F$13:$AB$50,MATCH(SOCI!$B21,SOMCI!$B$13:$B$50,0),MATCH(SOCI!I$8,SOMCI!$F$9:$AB$9,0)),"") -> 0 | K21: =SUM(F21:J21) -> 0
B22: =SOMCI!B24 -> Admin. Expenses | F22: =IFERROR(INDEX(SOMCI!$F$13:$AB$50,MATCH(SOCI!$B22,SOMCI!$B$13:$B$50,0),MATCH(SOCI!F$8,SOMCI!$F$9:$AB$9,0)),"") -> 85.666667 | G22: {=IFERROR(INDEX(SOMCI!$F$13:$AC$60,MATCH(SOCI!$B22,SOMCI!$B$13:$B$60,0),MATCH(0,(SOMCI!$F$9:$AC$9=SOCI!F$8)*(SOMCI!$F$10:$AC$10=SOCI!$G$9),1)),"")} -> 0 | I22: =IFERROR(INDEX(SOMCI!$F$13:$AB$50,MATCH(SOCI!$B22,SOMCI!$B$13:$B$50,0),MATCH(SOCI!I$8,SOMCI!$F$9:$AB$9,0)),"") -> 0 | K22: =SUM(F22:J22) -> 85.666667
B23: =SOMCI!B25 -> Legal & Professional Consultancy Service fee | F23: =IFERROR(INDEX(SOMCI!$F$13:$AB$50,MATCH(SOCI!$B23,SOMCI!$B$13:$B$50,0),MATCH(SOCI!F$8,SOMCI!$F$9:$AB$9,0)),"") -> 2000 | G23: {=IFERROR(INDEX(SOMCI!$F$13:$AC$60,MATCH(SOCI!$B23,SOMCI!$B$13:$B$60,0),MATCH(0,(SOMCI!$F$9:$AC$9=SOCI!F$8)*(SOMCI!$F$10:$AC$10=SOCI!$G$9),1)),"")} -> 0 | I23: =IFERROR(INDEX(SOMCI!$F$13:$AB$50,MATCH(SOCI!$B23,SOMCI!$B$13:$B$50,0),MATCH(SOCI!I$8,SOMCI!$F$9:$AB$9,0)),"") -> 0 | K23: =SUM(F23:J23) -> 2000
B24: =SOMCI!B26 -> Office Misc. Expenses | F24: =IFERROR(INDEX(SOMCI!$F$13:$AB$50,MATCH(SOCI!$B24,SOMCI!$B$13:$B$50,0),MATCH(SOCI!F$8,SOMCI!$F$9:$AB$9,0)),"") -> 0 | G24: {=IFERROR(INDEX(SOMCI!$F$13:$AC$60,MATCH(SOCI!$B24,SOMCI!$B$13:$B$60,0),MATCH(0,(SOMCI!$F$9:$AC$9=SOCI!F$8)*(SOMCI!$F$10:$AC$10=SOCI!$G$9),1)),"")} -> 0 | I24: =IFERROR(INDEX(SOMCI!$F$13:$AB$50,MATCH(SOCI!$B24,SOMCI!$B$13:$B$50,0),MATCH(SOCI!I$8,SOMCI!$F$9:$AB$9,0)),"") -> 0 | K24: =SUM(F24:J24) -> 0
B25: =SOMCI!B27 -> Trade License & Legal Expenses | F25: =IFERROR(INDEX(SOMCI!$F$13:$AB$50,MATCH(SOCI!$B25,SOMCI!$B$13:$B$50,0),MATCH(SOCI!F$8,SOMCI!$F$9:$AB$9,0)),"") -> 0 | G25: {=IFERROR(INDEX(SOMCI!$F$13:$AC$60,MATCH(SOCI!$B25,SOMCI!$B$13:$B$60,0),MATCH(0,(SOMCI!$F$9:$AC$9=SOCI!F$8)*(SOMCI!$F$10:$AC$10=SOCI!$G$9),1)),"")} -> 0 | I25: =IFERROR(INDEX(SOMCI!$F$13:$AB$50,MATCH(SOCI!$B25,SOMCI!$B$13:$B$50,0),MATCH(SOCI!I$8,SOMCI!$F$9:$AB$9,0)),"") -> 0 | K25: =SUM(F25:J25) -> 0
B26: =SOMCI!B28 -> Office Rent Expenses | F26: =IFERROR(INDEX(SOMCI!$F$13:$AB$50,MATCH(SOCI!$B26,SOMCI!$B$13:$B$50,0),MATCH(SOCI!F$8,SOMCI!$F$9:$AB$9,0)),"") -> 0 | G26: {=IFERROR(INDEX(SOMCI!$F$13:$AC$60,MATCH(SOCI!$B26,SOMCI!$B$13:$B$60,0),MATCH(0,(SOMCI!$F$9:$AC$9=SOCI!F$8)*(SOMCI!$F$10:$AC$10=SOCI!$G$9),1)),"")} -> 0 | I26: =IFERROR(INDEX(SOMCI!$F$13:$AB$50,MATCH(SOCI!$B26,SOMCI!$B$13:$B$50,0),MATCH(SOCI!I$8,SOMCI!$F$9:$AB$9,0)),"") -> 0 | K26: =SUM(F26:J26) -> 0
B27: =SOMCI!B29 -> Utility Expenses | F27: =IFERROR(INDEX(SOMCI!$F$13:$AB$50,MATCH(SOCI!$B27,SOMCI!$B$13:$B$50,0),MATCH(SOCI!F$8,SOMCI!$F$9:$AB$9,0)),"") -> 0 | G27: {=IFERROR(INDEX(SOMCI!$F$13:$AC$60,MATCH(SOCI!$B27,SOMCI!$B$13:$B$60,0),MATCH(0,(SOMCI!$F$9:$AC$9=SOCI!F$8)*(SOMCI!$F$10:$AC$10=SOCI!$G$9),1)),"")} -> 0 | I27: =IFERROR(INDEX(SOMCI!$F$13:$AB$50,MATCH(SOCI!$B27,SOMCI!$B$13:$B$50,0),MATCH(SOCI!I$8,SOMCI!$F$9:$AB$9,0)),"") -> 0 | K27: =SUM(F27:J27) -> 0
B28: =SOMCI!B30 -> Printing & Stationery | F28: =IFERROR(INDEX(SOMCI!$F$13:$AB$50,MATCH(SOCI!$B28,SOMCI!$B$13:$B$50,0),MATCH(SOCI!F$8,SOMCI!$F$9:$AB$9,0)),"") -> 1193.5 | G28: {=IFERROR(INDEX(SOMCI!$F$13:$AC$60,MATCH(SOCI!$B28,SOMCI!$B$13:$B$60,0),MATCH(0,(SOMCI!$F$9:$AC$9=SOCI!F$8)*(SOMCI!$F$10:$AC$10=SOCI!$G$9),1)),"")} -> 0 | I28: =IFERROR(INDEX(SOMCI!$F$13:$AB$50,MATCH(SOCI!$B28,SOMCI!$B$13:$B$50,0),MATCH(SOCI!I$8,SOMCI!$F$9:$AB$9,0)),"") -> 0 | K28: =SUM(F28:J28) -> 1193.5
B29: =SOMCI!B31 -> Meals & Refreshments General | F29: =IFERROR(INDEX(SOMCI!$F$13:$AB$50,MATCH(SOCI!$B29,SOMCI!$B$13:$B$50,0),MATCH(SOCI!F$8,SOMCI!$F$9:$AB$9,0)),"") -> 265.51333 | G29: {=IFERROR(INDEX(SOMCI!$F$13:$AC$60,MATCH(SOCI!$B29,SOMCI!$B$13:$B$60,0),MATCH(0,(SOMCI!$F$9:$AC$9=SOCI!F$8)*(SOMCI!$F$10:$AC$10=SOCI!$G$9),1)),"")} -> 0 | I29: =IFERROR(INDEX(SOMCI!$F$13:$AB$50,MATCH(SOCI!$B29,SOMCI!$B$13:$B$50,0),MATCH(SOCI!I$8,SOMCI!$F$9:$AB$9,0)),"") -> 0 | K29: =SUM(F29:J29) -> 265.51333
B30: =SOMCI!B32 -> Staff Medical Expenses | F30: =IFERROR(INDEX(SOMCI!$F$13:$AB$50,MATCH(SOCI!$B30,SOMCI!$B$13:$B$50,0),MATCH(SOCI!F$8,SOMCI!$F$9:$AB$9,0)),"") -> 4.8333333 | G30: {=IFERROR(INDEX(SOMCI!$F$13:$AC$60,MATCH(SOCI!$B30,SOMCI!$B$13:$B$60,0),MATCH(0,(SOMCI!$F$9:$AC$9=SOCI!F$8)*(SOMCI!$F$10:$AC$10=SOCI!$G$9),1)),"")} -> 0 | I30: =IFERROR(INDEX(SOMCI!$F$13:$AB$50,MATCH(SOCI!$B30,SOMCI!$B$13:$B$50,0),MATCH(SOCI!I$8,SOMCI!$F$9:$AB$9,0)),"") -> 0 | K30: =SUM(F30:J30) -> 4.8333333
B31: =SOMCI!B33 -> Travel & Transportation Expenses | F31: =IFERROR(INDEX(SOMCI!$F$13:$AB$50,MATCH(SOCI!$B31,SOMCI!$B$13:$B$50,0),MATCH(SOCI!F$8,SOMCI!$F$9:$AB$9,0)),"") -> 511.33333 | G31: {=IFERROR(INDEX(SOMCI!$F$13:$AC$60,MATCH(SOCI!$B31,SOMCI!$B$13:$B$60,0),MATCH(0,(SOMCI!$F$9:$AC$9=SOCI!F$8)*(SOMCI!$F$10:$AC$10=SOCI!$G$9),1)),"")} -> 0 | I31: =IFERROR(INDEX(SOMCI!$F$13:$AB$50,MATCH(SOCI!$B31,SOMCI!$B$13:$B$50,0),MATCH(SOCI!I$8,SOMCI!$F$9:$AB$9,0)),"") -> 0 | K31: =SUM(F31:J31) -> 511.33333
B32: =SOMCI!B34 -> Employee's Visa Expenses. | F32: =IFERROR(INDEX(SOMCI!$F$13:$AB$50,MATCH(SOCI!$B32,SOMCI!$B$13:$B$50,0),MATCH(SOCI!F$8,SOMCI!$F$9:$AB$9,0)),"") -> 1503.7533 | G32: {=IFERROR(INDEX(SOMCI!$F$13:$AC$60,MATCH(SOCI!$B32,SOMCI!$B$13:$B$60,0),MATCH(0,(SOMCI!$F$9:$AC$9=SOCI!F$8)*(SOMCI!$F$10:$AC$10=SOCI!$G$9),1)),"")} -> 0 | I32: =IFERROR(INDEX(SOMCI!$F$13:$AB$50,MATCH(SOCI!$B32,SOMCI!$B$13:$B$50,0),MATCH(SOCI!I$8,SOMCI!$F$9:$AB$9,0)),"") -> 0 | K32: =SUM(F32:J32) -> 1503.7533
... B35: =SOMCI!B37 -> Delivery Charges expenses | F35: =IFERROR(INDEX(SOMCI!$F$13:$AB$50,MATCH(SOCI!$B35,SOMCI!$B$13:$B$50,0),MATCH(SOCI!F$8,SOMCI!$F$9:$AB$9,0)),"") -> 12.333333 | G35: {=IFERROR(INDEX(SOMCI!$F$13:$AC$60,MATCH(SOCI!$B35,SOMCI!$B$13:$B$60,0),MATCH(0,(SOMCI!$F$9:$AC$9=SOCI!F$8)*(SOMCI!$F$10:$AC$10=SOCI!$G$9),1)),"")} -> 0 | I35: =IFERROR(INDEX(SOMCI!$F$13:$AB$50,MATCH(SOCI!$B35,SOMCI!$B$13:$B$50,0),MATCH(SOCI!I$8,SOMCI!$F$9:$AB$9,0)),"") -> 0 | K35: =SUM(F35:J35) -> 12.333333
A36: Other Expenses | F36: =SUM(F37:F40) -> 50000 | G36: =SUM(G37:G40) -> 0 | I36: =SUM(I37:I40) -> 0 | J36: =SUM(J37:J40) -> 0 | K36: =SUM(K37:K40) -> 50000
B37: =SOMCI!B39 -> Directors’ Remuneration | F37: =IFERROR(INDEX(SOMCI!$F$13:$AB$50,MATCH(SOCI!$B37,SOMCI!$B$13:$B$50,0),MATCH(SOCI!F$8,SOMCI!$F$9:$AB$9,0)),"") -> 50000 | G37: {=IFERROR(INDEX(SOMCI!$F$13:$AC$60,MATCH(SOCI!$B37,SOMCI!$B$13:$B$60,0),MATCH(0,(SOMCI!$F$9:$AC$9=SOCI!F$8)*(SOMCI!$F$10:$AC$10=SOCI!$G$9),1)),"")} -> 0 | H37: =IFERROR(INDEX(SOMCI!$F$13:$AB$50,MATCH(SOCI!$B37,SOMCI!$B$13:$B$50,0),MATCH(SOCI!H$8,SOMCI!$F$9:$AB$9,0)),"") | I37: =IFERROR(INDEX(SOMCI!$F$13:$AB$50,MATCH(SOCI!$B37,SOMCI!$B$13:$B$50,0),MATCH(SOCI!I$8,SOMCI!$F$9:$AB$9,0)),"") -> 0 | J37: =IFERROR(INDEX(SOMCI!$F$13:$AB$50,MATCH(SOCI!$B37,SOMCI!$B$13:$B$50,0),MATCH(SOCI!J$8,SOMCI!$F$9:$AB$9,0)),"") | K37: =SUM(F37:J37) -> 50000
B38: =SOMCI!B40 -> Bank Charges | F38: =IFERROR(INDEX(SOMCI!$F$13:$AB$50,MATCH(SOCI!$B38,SOMCI!$B$13:$B$50,0),MATCH(SOCI!F$8,SOMCI!$F$9:$AB$9,0)),"") -> 0 | G38: {=IFERROR(INDEX(SOMCI!$F$13:$AC$60,MATCH(SOCI!$B38,SOMCI!$B$13:$B$60,0),MATCH(0,(SOMCI!$F$9:$AC$9=SOCI!F$8)*(SOMCI!$F$10:$AC$10=SOCI!$G$9),1)),"")} -> 0 | I38: =IFERROR(INDEX(SOMCI!$F$13:$AB$50,MATCH(SOCI!$B38,SOMCI!$B$13:$B$50,0),MATCH(SOCI!I$8,SOMCI!$F$9:$AB$9,0)),"") -> 0 | K38: =SUM(F38:J38) -> 0
B39: =SOMCI!B41 -> WPS Charges | F39: =IFERROR(INDEX(SOMCI!$F$13:$AB$50,MATCH(SOCI!$B39,SOMCI!$B$13:$B$50,0),MATCH(SOCI!F$8,SOMCI!$F$9:$AB$9,0)),"") -> 0 | G39: {=IFERROR(INDEX(SOMCI!$F$13:$AC$60,MATCH(SOCI!$B39,SOMCI!$B$13:$B$60,0),MATCH(0,(SOMCI!$F$9:$AC$9=SOCI!F$8)*(SOMCI!$F$10:$AC$10=SOCI!$G$9),1)),"")} -> 0 | I39: =IFERROR(INDEX(SOMCI!$F$13:$AB$50,MATCH(SOCI!$B39,SOMCI!$B$13:$B$50,0),MATCH(SOCI!I$8,SOMCI!$F$9:$AB$9,0)),"") -> 0 | K39: =SUM(F39:J39) -> 0
B40: =SOMCI!B42 -> Fines & Mukhalfa | F40: =IFERROR(INDEX(SOMCI!$F$13:$AB$50,MATCH(SOCI!$B40,SOMCI!$B$13:$B$50,0),MATCH(SOCI!F$8,SOMCI!$F$9:$AB$9,0)),"") -> 0 | G40: {=IFERROR(INDEX(SOMCI!$F$13:$AC$60,MATCH(SOCI!$B40,SOMCI!$B$13:$B$60,0),MATCH(0,(SOMCI!$F$9:$AC$9=SOCI!F$8)*(SOMCI!$F$10:$AC$10=SOCI!$G$9),1)),"")} -> 0 | I40: =IFERROR(INDEX(SOMCI!$F$13:$AB$50,MATCH(SOCI!$B40,SOMCI!$B$13:$B$50,0),MATCH(SOCI!I$8,SOMCI!$F$9:$AB$9,0)),"") -> 0 | K40: =SUM(F40:J40) -> 0
A42: Profit / (Loss) before Interest , Dep. Other Income & Tax | F42: =+F10-F14-F20-F36 -> -4199.0733 | G42: =+G10-G14-G20-G36 -> 0 | H42: =+H10-H14-H20-H36 -> 0 | I42: =+I10-I14-I20-I36 -> 0 | J42: =+J10-J14-J20-J36 -> 0 | K42: =+K10-K14-K20-K36 -> -4199.0733
B43: Interest on Loans | F43: =IFERROR(INDEX(SOMCI!$F$13:$AB$50,MATCH(SOCI!$B43,SOMCI!$B$13:$B$50,0),MATCH(SOCI!F$8,SOMCI!$F$9:$AB$9,0)),"") -> 0 | G43: {=IFERROR(INDEX(SOMCI!$F$13:$AC$60,MATCH(SOCI!$B43,SOMCI!$B$13:$B$60,0),MATCH(0,(SOMCI!$F$9:$AC$9=SOCI!F$8)*(SOMCI!$F$10:$AC$10=SOCI!$G$9),1)),"")} -> 0 | I43: 0 | K43: =SUM(F43:J43) -> 0
A44: Profit/ (Loss) After Interest but before Dep. Other Income & Tax | F44: =+F42-F43 -> -4199.0733 | G44: =+G42-G43 -> 0 | H44: =+H42-H43 -> 0 | I44: =+I42-I43 -> 0 | J44: =+J42-J43 -> 0 | K44: =+K42-K43 -> -4199.0733
B45: Depreciation | F45: =IFERROR(INDEX(SOMCI!$F$13:$AB$50,MATCH(SOCI!$B45,SOMCI!$B$13:$B$50,0),MATCH(SOCI!F$8,SOMCI!$F$9:$AB$9,0)),"") -> 12500 | G45: {=IFERROR(INDEX(SOMCI!$F$13:$AC$60,MATCH(SOCI!$B45,SOMCI!$B$13:$B$60,0),MATCH(0,(SOMCI!$F$9:$AC$9=SOCI!F$8)*(SOMCI!$F$10:$AC$10=SOCI!$G$9),1)),"")} -> 0 | I45: 0 | K45: =SUM(F45:J45) -> 12500
A46: Profit/ (Loss) After Dep. but before Other Income & Tax | F46: =+F44-F45 -> -16699.073 | G46: =+G44-G45 -> 0 | H46: =+H44-H45 -> 0 | I46: =+I44-I45 -> 0 | K46: =+K44-K45 -> -16699.073
B47: =SOMCI!B48 -> Other Income | F47: =IFERROR(INDEX(SOMCI!$F$13:$AB$50,MATCH(SOCI!$B47,SOMCI!$B$13:$B$50,0),MATCH(SOCI!F$8,SOMCI!$F$9:$AB$9,0)),"") -> 0 | G47: {=IFERROR(INDEX(SOMCI!$F$13:$AC$60,MATCH(SOCI!$B47,SOMCI!$B$13:$B$60,0),MATCH(0,(SOMCI!$F$9:$AC$9=SOCI!F$8)*(SOMCI!$F$10:$AC$10=SOCI!$G$9),1)),"")} -> 0 | I47: =IFERROR(INDEX(SOMCI!$F$13:$AB$50,MATCH(SOCI!$B47,SOMCI!$B$13:$B$50,0),MATCH(SOCI!I$8,SOMCI!$F$9:$AB$9,0)),"") -> 0 | K47: =SUM(F47:J47) -> 0
A48: Profit/ (Loss) After Other Income but before Tax | F48: =+F46-F47 -> -16699.073 | G48: =+G46-G47 -> 0 | H48: =+H46-H47 -> 0 | I48: =+I46-I47 -> 0 | J48: =+J46-J47 -> 0 | K48: =IFERROR(K46+K47,0) -> -16699.073
B49: Corporate Tax | F49: =IFERROR(INDEX(SOMCI!$F$13:$AB$50,MATCH(SOCI!$B49,SOMCI!$B$13:$B$50,0),MATCH(SOCI!F$8,SOMCI!$F$9:$AB$9,0)),"") -> 0 | G49: {=IFERROR(INDEX(SOMCI!$F$13:$AC$60,MATCH(SOCI!$B49,SOMCI!$B$13:$B$60,0),MATCH(0,(SOMCI!$F$9:$AC$9=SOCI!F$8)*(SOMCI!$F$10:$AC$10=SOCI!$G$9),1)),"")} -> 0 | K49: =SUM(F49:J49) -> 0
A50: Net Profit / (Loss) | F50: =+F48-F49 -> -16699.073 | G50: =+G48-G49 -> 0 | H50: =+H48-H49 -> 0 | I50: =+I48-I49 -> 0 | J50: =+J48-J49 -> 0 | K50: =IFERROR(K48+K49,0) -> -16699.073
L52: =K48-SOMCI!AD49 -> 0

Sheet SOMCI
A2: =Cover!A9 -> Afrodiva Exotic Hair Boutique Ltd.
A3: =Cover!A10 -> DUABI UAE
A5: STATEMENT OF MONTHLY COMPREHENSIVE INCOME
A6: =SOCI!A6 -> For the month of January - 2026
A8: Amount in AED
A9: Particulars | D9: Notes | F9: 45689 | H9: =DATE(YEAR(F9),MONTH(F9)+1,1) -> 45717 | J9: =DATE(YEAR(H9),MONTH(H9)+1,1) -> 45748 | L9: =DATE(YEAR(J9),MONTH(J9)+1,1) -> 45778 | N9: =DATE(YEAR(L9),MONTH(L9)+1,1) -> 45809 | P9: =DATE(YEAR(N9),MONTH(N9)+1,1) -> 45839 | R9: =DATE(YEAR(P9),MONTH(P9)+1,1) -> 45870 | T9: =DATE(YEAR(R9),MONTH(R9)+1,1) -> 45901 | V9: =DATE(YEAR(T9),MONTH(T9)+1,1) -> 45931 | X9: =DATE(YEAR(V9),MONTH(V9)+1,1) -> 45962 | Z9: =DATE(YEAR(X9),MONTH(X9)+1,1) -> 45992 | AB9: =DATE(YEAR(Z9),MONTH(Z9)+1,1) -> 46023 | AD9: YTD
F10: DIFC | G10: Al Barsha | H10: DIFC | I10: Al Barsha | J10: DIFC | K10: Al Barsha | L10: DIFC | M10: Al Barsha | N10: DIFC | O10: Al Barsha | P10: DIFC | Q10: Al Barsha | R10: DIFC | S10: Al Barsha | T10: DIFC | U10: Al Barsha | V10: DIFC | W10: Al Barsha | X10: DIFC | Y10: Al Barsha | Z10: DIFC | AA10: Al Barsha | AB10: DIFC | AC10: Al Barsha
A12: Revenue | F12: =SUM(F13:F14) -> 0 | H12: =SUM(H13:H14) -> 0 | J12: =SUM(J13:J14) -> 0 | L12: =SUM(L13:L14) -> 0 | N12: =SUM(N13:N14) -> 0 | P12: =SUM(P13:P14) -> 0 | R12: =SUM(R13:R14) -> 0 | T12: =SUM(T13:T14) -> 0 | V12: =SUM(V13:V14) -> 0 | X12: =SUM(X13:X14) -> 0 | Z12: =SUM(Z13:Z14) -> 0 | AB12: =SUM(AB13:AB14)-AB15 -> 87643.893 | AC12: =SUM(AC13:AC14)-AC15 -> 0 | AD12: =SUM(F12:AC12) -> 87643.893
B13: ='Linked IS'!A4 -> Sales | F13: 0 | H13: 0 | J13: 0 | L13: 0 | N13: 0 | P13: 0 | R13: 0 | T13: 0 | V13: 0 | X13: 0 | Z13: 0 | AA13: 0 | AB13: =IFERROR(VLOOKUP(B13,'Linked IS'!$A$1:$B$51,2,0),0) -> 87643.893 | AC13: =IFERROR(VLOOKUP(B13,'Linked IS'!$A$1:$C$51,3,0),0) -> 0 | AD13: =SUM(F13:AC13) -> 87643.893
B14: ='Linked IS'!A5 -> E-Commerce's/Online Sale | F14: 0 | H14: 0 | J14: 0 | L14: 0 | N14: 0 | P14: 0 | R14: 0 | T14: 0 | V14: 0 | X14: 0 | Z14: 0 | AA14: 0 | AB14: =IFERROR(VLOOKUP(B14,'Linked IS'!$A$1:$B$51,2,0),0) -> 0 | AC14: =IFERROR(VLOOKUP(B14,'Linked IS'!$A$1:$C$51,3,0),0) -> 0 | AD14: =SUM(F14:AC14) -> 0
B15: Sales Discounts | AB15: =IFERROR(VLOOKUP(B15,'Linked IS'!$A$1:$B$51,2,0),0) -> 0 | AC15: =IFERROR(VLOOKUP(B15,'Linked IS'!$A$1:$C$51,3,0),0) -> 0 | AD15: =SUM(F15:AC15) -> 0
A16: Direct Expenses | F16: =SUM(F17:F19) -> 0 | G16: =SUM(G17:G19) -> 0 | H16: =SUM(H17:H19) -> 0 | I16: =SUM(I17:I19) -> 0 | J16: =SUM(J17:J19) -> 0 | K16: =SUM(K17:K19) -> 0 | L16: =SUM(L17:L19) -> 0 | M16: =SUM(M17:M19) -> 0 | ... AC16: =SUM(AC17:AC19) -> 0 | AD16: =SUM(F16:AC16) -> 35045.157
AD17: =SUM(F17:AB17) -> 0
B18: Cost of Sales | F18: 0 | H18: 0 | J18: 0 | L18: 0 | N18: 0 | P18: 0 | R18: 0 | T18: 0 | V18: 0 | X18: 0 | Z18: 0 | AA18: 0 | AB18: =IFERROR(VLOOKUP(B18,'Linked IS'!$A$1:$B$51,2,0),0) -> 35045.157 | AC18: =IFERROR(VLOOKUP(B18,'Linked IS'!$A$1:$C$51,3,0),0) -> 0 | AD18: =SUM(F18:AC18) -> 35045.157
AD19: =SUM(F19:AB19) -> 0
A20: Gross Profit / (Loss) | F20: =+F12-F16 -> 0 | H20: =+H12-H16 -> 0 | J20: =+J12-J16 -> 0 | L20: =+L12-L16 -> 0 | N20: =+N12-N16 -> 0 | P20: =+P12-P16 -> 0 | R20: =+R12-R16 -> 0 | T20: =+T12-T16 -> 0 | V20: =+V12-V16 -> 0 | X20: =+X12-X16 -> 0 | Z20: =+Z12-Z16 -> 0 | AA20: =+AA12-AA16 -> 0 | AB20: =+AB12-AB16 -> 52598.737 | AD20: =SUM(F20:AC20) -> 52598.737
A21: Indirect Expenses | F21: =+F22+F38 -> 0 | G21: =+G22+G38 -> 0 | H21: =+H22+H38 -> 0 | I21: =+I22+I38 -> 0 | J21: =+J22+J38 -> 0 | K21: =+K22+K38 -> 0 | L21: =+L22+L38 -> 0 | M21: =+M22+M38 -> 0 | ... AC21: =+AC22+AC38 -> 0 | AD21: =SUM(F21:AC21) -> 56797.81
A22: Operating & Administrative Exp. | F22: =SUM(F23:F37) -> 0 | H22: =SUM(H23:H37) -> 0 | J22: =SUM(J23:J37) -> 0 | L22: =SUM(L23:L37) -> 0 | N22: =SUM(N23:N37) -> 0 | P22: =SUM(P23:P37) -> 0 | R22: =SUM(R23:R37) -> 0 | T22: =SUM(T23:T37) -> 0 | V22: =SUM(V23:V37) -> 0 | X22: =SUM(X23:X37) -> 0 | Z22: =SUM(Z23:Z37) -> 0 | AA22: =SUM(AA23:AA37) -> 0 | AB22: =SUM(AB23:AB37) -> 6797.81 | AC22: =SUM(AC23:AC37) -> 0 | AD22: =SUM(F22:AB22) -> 6797.81
B23: ='Linked IS'!A18 -> Salary & wages | F23: 0 | H23: 0 | J23: 0 | L23: 0 | N23: 0 | P23: 0 | R23: 0 | T23: 0 | V23: 0 | X23: 0 | Z23: 0 | AA23: 0 | AB23: =IFERROR(VLOOKUP(B23,'Linked IS'!$A$1:$B$43,2,0),0) -> 0 | AC23: =IFERROR(VLOOKUP(B23,'Linked IS'!$A$1:$C$43,3,0),0) -> 0 | AD23: =SUM(F23:AC23) -> 0
B24: ='Linked IS'!A19 -> Admin. Expenses | F24: 0 | H24: 0 | J24: 0 | L24: 0 | N24: 0 | P24: 0 | R24: 0 | T24: 0 | V24: 0 | X24: 0 | Z24: 0 | AA24: 0 | AB24: =IFERROR(VLOOKUP(B24,'Linked IS'!$A$1:$B$43,2,0),0) -> 85.666667 | AC24: =IFERROR(VLOOKUP(B24,'Linked IS'!$A$1:$C$43,3,0),0) -> 0 | AD24: =SUM(F24:AC24) -> 85.666667
B25: ='Linked IS'!A20 -> Legal & Professional Consultancy Service fee | F25: 0 | H25: 0 | J25: 0 | L25: 0 | N25: 0 | P25: 0 | R25: 0 | T25: 0 | V25: 0 | X25: 0 | Z25: 0 | AA25: 0 | AB25: =IFERROR(VLOOKUP(B25,'Linked IS'!$A$1:$B$43,2,0),0) -> 2000 | AC25: =IFERROR(VLOOKUP(B25,'Linked IS'!$A$1:$C$43,3,0),0) -> 0 | AD25: =SUM(F25:AC25) -> 2000
B26: ='Linked IS'!A21 -> Office Misc. Expenses | F26: 0 | H26: 0 | J26: 0 | L26: 0 | N26: 0 | P26: 0 | R26: 0 | T26: 0 | V26: 0 | X26: 0 | Z26: 0 | AA26: 0 | AB26: =IFERROR(VLOOKUP(B26,'Linked IS'!$A$1:$B$43,2,0),0) -> 0 | AC26: =IFERROR(VLOOKUP(B26,'Linked IS'!$A$1:$C$43,3,0),0) -> 0 | AD26: =SUM(F26:AC26) -> 0
B27: ='Linked IS'!A22 -> Trade License & Legal Expenses | F27: 0 | H27: 0 | J27: 0 | L27: 0 | N27: 0 | P27: 0 | R27: 0 | T27: 0 | V27: 0 | X27: 0 | Z27: 0 | AA27: 0 | AB27: =IFERROR(VLOOKUP(B27,'Linked IS'!$A$1:$B$43,2,0),0) -> 0 | AC27: =IFERROR(VLOOKUP(B27,'Linked IS'!$A$1:$C$43,3,0),0) -> 0 | AD27: =SUM(F27:AC27) -> 0
B28: ='Linked IS'!A23 -> Office Rent Expenses | F28: 0 | H28: 0 | J28: 0 | L28: 0 | N28: 0 | P28: 0 | R28: 0 | T28: 0 | V28: 0 | X28: 0 | Z28: 0 | AA28: 0 | AB28: =IFERROR(VLOOKUP(B28,'Linked IS'!$A$1:$B$43,2,0),0) -> 0 | AC28: =IFERROR(VLOOKUP(B28,'Linked IS'!$A$1:$C$43,3,0),0) -> 0 | AD28: =SUM(F28:AC28) -> 0
B29: ='Linked IS'!A24 -> Utility Expenses | F29: 0 | H29: 0 | J29: 0 | L29: 0 | N29: 0 | P29: 0 | R29: 0 | T29: 0 | V29: 0 | X29: 0 | Z29: 0 | AA29: 0 | AB29: =IFERROR(VLOOKUP(B29,'Linked IS'!$A$1:$B$43,2,0),0) -> 0 | AC29: =IFERROR(VLOOKUP(B29,'Linked IS'!$A$1:$C$43,3,0),0) -> 0 | AD29: =SUM(F29:AC29) -> 0
B30: ='Linked IS'!A25 -> Printing & Stationery | F30: 0 | H30: 0 | J30: 0 | L30: 0 | N30: 0 | P30: 0 | R30: 0 | T30: 0 | V30: 0 | X30: 0 | Z30: 0 | AA30: 0 | AB30: =IFERROR(VLOOKUP(B30,'Linked IS'!$A$1:$B$43,2,0),0) -> 1193.5 | AC30: =IFERROR(VLOOKUP(B30,'Linked IS'!$A$1:$C$43,3,0),0) -> 0 | AD30: =SUM(F30:AC30) -> 1193.5
B31: ='Linked IS'!A26 -> Meals & Refreshments General | F31: 0 | H31: 0 | J31: 0 | L31: 0 | N31: 0 | P31: 0 | R31: 0 | T31: 0 | V31: 0 | X31: 0 | Z31: 0 | AA31: 0 | AB31: =IFERROR(VLOOKUP(B31,'Linked IS'!$A$1:$B$43,2,0),0) -> 265.51333 | AC31: =IFERROR(VLOOKUP(B31,'Linked IS'!$A$1:$C$43,3,0),0) -> 0 | AD31: =SUM(F31:AC31) -> 265.51333
B32: ='Linked IS'!A27 -> Staff Medical Expenses | F32: 0 | H32: 0 | J32: 0 | L32: 0 | N32: 0 | P32: 0 | R32: 0 | T32: 0 | V32: 0 | X32: 0 | Z32: 0 | AA32: 0 | AB32: =IFERROR(VLOOKUP(B32,'Linked IS'!$A$1:$B$43,2,0),0) -> 4.8333333 | AC32: =IFERROR(VLOOKUP(B32,'Linked IS'!$A$1:$C$43,3,0),0) -> 0 | AD32: =SUM(F32:AC32) -> 4.8333333
B33: ='Linked IS'!A28 -> Travel & Transportation Expenses | F33: 0 | H33: 0 | J33: 0 | L33: 0 | N33: 0 | P33: 0 | R33: 0 | T33: 0 | V33: 0 | X33: 0 | Z33: 0 | AA33: 0 | AB33: =IFERROR(VLOOKUP(B33,'Linked IS'!$A$1:$B$43,2,0),0) -> 511.33333 | AC33: =IFERROR(VLOOKUP(B33,'Linked IS'!$A$1:$C$43,3,0),0) -> 0 | AD33: =SUM(F33:AC33) -> 511.33333
B34: ='Linked IS'!A29 -> Employee's Visa Expenses. | F34: 0 | H34: 0 | J34: 0 | L34: 0 | N34: 0 | P34: 0 | R34: 0 | T34: 0 | V34: 0 | X34: 0 | Z34: 0 | AA34: 0 | AB34: =IFERROR(VLOOKUP(B34,'Linked IS'!$A$1:$B$43,2,0),0) -> 1503.7533 | AC34: =IFERROR(VLOOKUP(B34,'Linked IS'!$A$1:$C$43,3,0),0) -> 0 | AD34: =SUM(F34:AC34) -> 1503.7533
... B37: ='Linked IS'!A32 -> Delivery Charges expenses | F37: 0 | H37: 0 | J37: 0 | L37: 0 | N37: 0 | P37: 0 | R37: 0 | T37: 0 | V37: 0 | X37: 0 | Z37: 0 | AA37: 0 | AB37: =IFERROR(VLOOKUP(B37,'Linked IS'!$A$1:$B$43,2,0),0) -> 12.333333 | AC37: =IFERROR(VLOOKUP(B37,'Linked IS'!$A$1:$C$43,3,0),0) -> 0 | AD37: =SUM(F37:AC37) -> 12.333333
A38: Other Expenses | F38: =SUM(F40:F42) -> 0 | H38: =SUM(H40:H42) -> 0 | J38: =SUM(J40:J42) -> 0 | L38: =SUM(L40:L42) -> 0 | N38: =SUM(N40:N42) -> 0 | P38: =SUM(P40:P42) -> 0 | R38: =SUM(R40:R42) -> 0 | T38: =SUM(T40:T42) -> 0 | V38: =SUM(V40:V42) -> 0 | X38: =SUM(X40:X42) -> 0 | Z38: =SUM(Z40:Z42) -> 0 | AA38: =SUM(AA40:AA42) -> 0 | AB38: =SUM(AB39:AB42) -> 50000 | AC38: =SUM(AC39:AC42) -> 0 | AD38: =SUM(F38:AC38) -> 50000
B39: ='Linked IS'!A36 -> Directors’ Remuneration | Z39: 0 | AA39: 0 | AB39: =IFERROR(VLOOKUP(B39,'Linked IS'!$A$1:$B$43,2,0),0) -> 50000 | AC39: =IFERROR(VLOOKUP(B39,'Linked IS'!$A$1:$C$43,3,0),0) -> 0 | AD39: =SUM(F39:AC39) -> 50000
B40: ='Linked IS'!A37 -> Bank Charges | F40: 0 | H40: 0 | J40: 0 | L40: 0 | N40: 0 | P40: 0 | R40: 0 | T40: 0 | V40: 0 | X40: 0 | Z40: 0 | AA40: 0 | AB40: =IFERROR(VLOOKUP(B40,'Linked IS'!$A$1:$B$43,2,0),0) -> 0 | AC40: =IFERROR(VLOOKUP(B40,'Linked IS'!$A$1:$C$43,3,0),0) -> 0 | AD40: =SUM(F40:AC40) -> 0
B41: ='Linked IS'!A38 -> WPS Charges | F41: 0 | H41: 0 | J41: 0 | L41: 0 | N41: 0 | P41: 0 | R41: 0 | T41: 0 | V41: 0 | X41: 0 | Z41: 0 | AA41: 0 | AB41: =IFERROR(VLOOKUP(B41,'Linked IS'!$A$1:$B$43,2,0),0) -> 0 | AC41: =IFERROR(VLOOKUP(B41,'Linked IS'!$A$1:$C$43,3,0),0) -> 0 | AD41: =SUM(F41:AC41) -> 0
B42: ='Linked IS'!A40 -> Fines & Mukhalfa | F42: 0 | H42: 0 | J42: 0 | L42: 0 | N42: 0 | P42: 0 | R42: 0 | T42: 0 | V42: 0 | X42: 0 | Z42: 0 | AA42: 0 | AB42: =IFERROR(VLOOKUP(B42,'Linked IS'!$A$1:$B$43,2,0),0) -> 0 | AC42: =IFERROR(VLOOKUP(B42,'Linked IS'!$A$1:$C$43,3,0),0) -> 0 | AD42: =SUM(F42:AC42) -> 0
A43: Profit / (Loss) before Interest , Dep. Other Income & Tax | F43: =+F12-F16-F22-F38 -> 0 | G43: =+G12-G16-G22-G38 -> 0 | H43: =+H12-H16-H22-H38 -> 0 | I43: =+I12-I16-I22-I38 -> 0 | J43: =+J12-J16-J22-J38 -> 0 | K43: =+K12-K16-K22-K38 -> 0 | L43: =+L12-L16-L22-L38 -> 0 | M43: =+M12-M16-M22-M38 -> 0 | ... AC43: =+AC12-AC16-AC22-AC38 -> 0 | AD43: =SUM(F43:AC43) -> -4199.0733
B44: Interest on Loans | F44: 0 | H44: 0 | J44: 0 | L44: 0 | N44: 0 | P44: 0 | R44: 0 | T44: 0 | V44: 0 | X44: 0 | Z44: 0 | AA44: 0 | AB44: =IFERROR(VLOOKUP(B44,'Linked IS'!$A$1:$B$52,2,0),0) -> 0 | AC44: =IFERROR(VLOOKUP(B44,'Linked IS'!$A$1:$C$52,3,0),0) -> 0
A45: Profit/ (Loss) After Interest but before Dep. Other Income & Tax | F45: =+F43-F44 -> 0 | H45: =+H43-H44 -> 0 | J45: =+J43-J44 -> 0 | L45: =+L43-L44 -> 0 | N45: =+N43-N44 -> 0 | P45: =+P43-P44 -> 0 | R45: =+R43-R44 -> 0 | T45: =+T43-T44 -> 0 | V45: =+V43-V44 -> 0 | X45: =+X43-X44 -> 0 | Z45: =+Z43-Z44 -> 0 | AA45: =+AA43-AA44 -> 0 | AB45: =+AB43-AB44 -> -4199.0733 | AC45: =+AC43-AC44 -> 0 | AD45: =SUM(F45:AC45) -> -4199.0733
B46: Depreciation | F46: 0 | H46: 0 | J46: 0 | L46: 0 | N46: 0 | P46: 0 | R46: 0 | T46: 0 | V46: 0 | X46: 0 | Z46: 0 | AA46: 0 | AB46: =IFERROR(VLOOKUP(B46,'Linked IS'!$A$1:$B$52,2,0),0) -> 12500 | AC46: =IFERROR(VLOOKUP(B46,'Linked IS'!$A$1:$C$52,3,0),0) -> 0
A47: Profit/ (Loss) After Dep. but before Other Income & Tax | F47: 0 | H47: 0 | J47: 0 | L47: 0 | N47: 0 | P47: 0 | R47: 0 | T47: 0 | V47: 0 | X47: 0 | Z47: 0 | AA47: 0 | AB47: =+AB45-AB46 -> -16699.073 | AC47: =+AC45-AC46 -> 0 | AD47: =SUM(F47:AC47) -> -16699.073
B48: Other Income | F48: 0 | H48: 0 | J48: 0 | L48: 0 | N48: 0 | P48: 0 | R48: 0 | T48: 0 | V48: 0 | X48: 0 | Z48: 0 | AA48: 0 | AB48: =IFERROR(VLOOKUP(B48,'Linked IS'!$A$1:$B$52,2,0),0) -> 0 | AC48: =IFERROR(VLOOKUP(B48,'Linked IS'!$A$1:$C$52,3,0),0) -> 0 | AD48: =SUM(F48:AB48) -> 0
A49: Profit/ (Loss) After Other Income but before Tax | F49: =+F47+F48 -> 0 | H49: =+H47+H48 -> 0 | J49: =+J47+J48 -> 0 | L49: =+L47+L48 -> 0 | N49: =+N47+N48 -> 0 | P49: =+P47+P48 -> 0 | R49: =+R47+R48 -> 0 | T49: =+T47+T48 -> 0 | V49: =+V47+V48 -> 0 | X49: =+X47+X48 -> 0 | Z49: =+Z47+Z48 -> 0 | AA49: =+AA47+AA48 -> 0 | AB49: =+AB47+AB48 -> -16699.073 | AC49: =+AC47+AC48 -> 0 | AD49: =SUM(F49:AC49) -> -16699.073
B50: Corporate Tax | AB50: =IFERROR(VLOOKUP(B50,'Linked IS'!$A$1:$B$52,2,0),0) -> 0 | AC50: =IFERROR(VLOOKUP(B50,'Linked IS'!$A$1:$C$52,3,0),0) -> 0
A51: Net Profit / (Loss) | AB51: =+AB49+AB50 -> -16699.073 | AC51: =+AC49+AC50 -> 0 | AD51: =SUM(F51:AC51) -> -16699.073 | AG51: =AD51-'Linked IS'!B45 -> 6.6666471e-06

Sheet Budget
A2: =Cover!A9 -> Afrodiva Exotic Hair Boutique Ltd.
A3: =Cover!A10 -> DUABI UAE
C5: =SOCI!F8 -> 46023 | G5: YEAR-TO-DATE | K5: Note: All variances of +-10% must be explained in remarks.
A6: DESCRIPTION | B6: BUDGET | C6: ACTUAL | D6: VARIANCE | E6: % | G6: BUDGET | H6: ACTUAL | I6: VARIANCE | J6: % | K6: Remarks
A8: Revenues: | B8: =SUM(B9:B12) -> 0 | C8: =SUM(C9:C12) -> 0 | D8: =B8-C8 -> 0 | E8: =IFERROR(+D8*100/B8,0) -> 0 | G8: =SUM(G9:G12) -> 0 | H8: =IFERROR(SUM(H9:H12),0) -> 0 | I8: =+H8-G8 -> 0 | J8: =IFERROR(+I8*100/G8,0) -> 0 | K8: EFFICIENCY VARIANCE
A9: Sales Product 1 | D9: =C9-B9 -> 0 | E9: =IFERROR(+D9*100/B9,0) -> 0 | G9: =+B9*5 -> 0 | H9: 0 | I9: =H9-G9 -> 0 | J9: =IFERROR(+I9*100/G9,0) -> 0
A10: Sales Product 2 | D10: =C10-B10 -> 0 | E10: =IFERROR(+D10*100/B10,0) -> 0 | G10: =+B10*5 -> 0 | H10: 0 | I10: =H10-G10 -> 0 | J10: =IFERROR(+I10*100/G10,0) -> 0
A11: Sales Product 3 | D11: =C11-B11 -> 0 | E11: =IFERROR(+D11*100/B11,0) -> 0 | G11: =+B11*5 -> 0 | H11: 0 | I11: =H11-G11 -> 0 | J11: =IFERROR(+I11*100/G11,0) -> 0
A12: Sales Product 4 | D12: =C12-B12 -> 0 | E12: =IFERROR(+D12*100/B12,0) -> 0 | G12: 0 | H12: 0 | I12: =H12-G12 -> 0 | J12: =IFERROR(+I12*100/G12,0) -> 0
A14: Fixed Expenses | B14: =SUM(B15:B17) -> 0 | C14: =SUM(C15:C17) -> 0 | D14: =+B14-C14 -> 0 | E14: =IFERROR(+D14*100/B14,0) -> 0 | G14: =SUM(G15:G17) -> 0 | H14: =SUM(H15:H17) -> 0 | I14: =+G14-H14 -> 0 | J14: =IFERROR(+I14*100/G14,0) -> 0 | K14: EXCEPTIONAL VARIANCE
A15: Salaries | C15: 0 | D15: =+B15-C15 -> 0 | E15: =IFERROR(+D15*100/B15,0) -> 0 | I15: =+G15-H15 -> 0 | J15: =IFERROR(+I15*100/G15,0) -> 0
A16: Office Rent | B16: 0 | C16: 0 | D16: =+B16-C16 -> 0 | E16: =IFERROR(+D16*100/B16,0) -> 0 | I16: =+G16-H16 -> 0 | J16: =IFERROR(+I16*100/G16,0) -> 0
A17: Others | B17: 0 | C17: 0 | D17: 0 | E17: =IFERROR(+D17*100/B17,0) -> 0 | I17: 0 | J17: =IFERROR(+I17*100/G17,0) -> 0
A19: Variable Expenses | B19: =SUM(B20:B41) -> 0 | C19: =SUM(C20:C41) -> 0 | D19: =+B19-C19 -> 0 | E19: =IFERROR((+D19*100/B19),0) -> 0 | G19: =SUM(G20:G41) -> 0 | H19: =SUM(H20:H41) -> 0 | I19: =+G19-H19 -> 0 | J19: =IFERROR((+I19*100/G19),0) -> 0 | K19: EFFICIENCY VARIANCE
A20: Annual leave | D20: =+B20-C20 -> 0 | E20: =IFERROR((+D20*100/B20),0) -> 0 | I20: =+G20-H20 -> 0 | J20: =IFERROR((+I20*100/G20),0) -> 0
A21: Car lease instalments /Rental | D21: =+B21-C21 -> 0 | E21: =IFERROR((+D21*100/B21),0) -> 0 | I21: =+G21-H21 -> 0 | J21: =IFERROR((+I21*100/G21),0) -> 0
A22: Commission - Agent | D22: =+B22-C22 -> 0 | E22: =IFERROR((+D22*100/B22),0) -> 0 | I22: =+G22-H22 -> 0 | J22: =IFERROR((+I22*100/G22),0) -> 0
A23: Commission - Third party | D23: =+B23-C23 -> 0 | E23: =IFERROR((+D23*100/B23),0) -> 0 | I23: =+G23-H23 -> 0 | J23: =IFERROR((+I23*100/G23),0) -> 0
A24: Depreciation | D24: =+B24-C24 -> 0 | E24: =IFERROR((+D24*100/B24),0) -> 0 | I24: =+G24-H24 -> 0 | J24: =IFERROR((+I24*100/G24),0) -> 0
A25: DEWA - Electricity bill | E25: =IFERROR((+D25*100/B25),0) -> 0 | J25: =IFERROR((+I25*100/G25),0) -> 0
A26: Financial Charges | E26: =IFERROR((+D26*100/B26),0) -> 0 | J26: =IFERROR((+I26*100/G26),0) -> 0
A27: Internal Audit Fees / (Provision) | D27: =+B27-C27 -> 0 | E27: =IFERROR((+D27*100/B27),0) -> 0 | I27: =+G27-H27 -> 0 | J27: =IFERROR((+I27*100/G27),0) -> 0
A28: IT Expenses | D28: =+B28-C28 -> 0 | E28: =IFERROR((+D28*100/B28),0) -> 0 | I28: =+G28-H28 -> 0 | J28: =IFERROR((+I28*100/G28),0) -> 0
A29: Legal & Professional Fees | D29: =+B29-C29 -> 0 | E29: =IFERROR((+D29*100/B29),0) -> 0 | I29: =+G29-H29 -> 0 | J29: =IFERROR((+I29*100/G29),0) -> 0
A30: Marketing & Advertisment | D30: =+B30-C30 -> 0 | E30: =IFERROR((+D30*100/B30),0) -> 0 | I30: =+G30-H30 -> 0 | J30: =IFERROR((+I30*100/G30),0) -> 0
A31: Office Exp. | D31: =+B31-C31 -> 0 | E31: =IFERROR((+D31*100/B31),0) -> 0 | I31: =+G31-H31 -> 0 | J31: =IFERROR((+I31*100/G31),0) -> 0
A32: Office Insurance Exp. | D32: =+B32-C32 -> 0 | E32: =IFERROR((+D32*100/B32),0) -> 0 | I32: =+G32-H32 -> 0 | J32: =IFERROR((+I32*100/G32),0) -> 0
A33: Printing & Stationary | D33: =+B33-C33 -> 0 | E33: =IFERROR((+D33*100/B33),0) -> 0 | I33: =+G33-H33 -> 0 | J33: =IFERROR((+I33*100/G33),0) -> 0
A34: Security Charges | D34: =+B34-C34 -> 0 | E34: =IFERROR((+D34*100/B34),0) -> 0 | I34: =+G34-H34 -> 0 | J34: =IFERROR((+I34*100/G34),0) -> 0
A35: Staff Medical | D35: =+B35-C35 -> 0 | E35: =IFERROR((+D35*100/B35),0) -> 0 | I35: =+G35-H35 -> 0 | J35: =IFERROR((+I35*100/G35),0) -> 0
A36: Taxes | D36: =+B36-C36 -> 0 | E36: =IFERROR((+D36*100/B36),0) -> 0 | I36: =+G36-H36 -> 0 | J36: =IFERROR((+I36*100/G36),0) -> 0
A37: Telephone & Internet Exp. | D37: =+B37-C37 -> 0 | E37: =IFERROR((+D37*100/B37),0) -> 0 | I37: =+G37-H37 -> 0 | J37: =IFERROR((+I37*100/G37),0) -> 0
A38: Transportation | D38: =+B38-C38 -> 0 | E38: =IFERROR((+D38*100/B38),0) -> 0 | I38: =+G38-H38 -> 0 | J38: =IFERROR((+I38*100/G38),0) -> 0
A39: Visa & Ticket | D39: =+B39-C39 -> 0 | E39: =IFERROR((+D39*100/B39),0) -> 0 | J39: =IFERROR((+I39*100/G39),0) -> 0
A40: WPS charges | D40: =+B40-C40 -> 0 | E40: =IFERROR((+D40*100/B40),0) -> 0 | J40: =IFERROR((+I40*100/G40),0) -> 0
D41: =+B41-C41 -> 0 | E41: =IFERROR((+D41*100/B41),0) -> 0 | I41: =+G41-H41 -> 0 | J41: =IFERROR((+I41*100/G41),0) -> 0
A42: Total Expenses: (Fixed + Variable) | B42: =+B14+B19 -> 0 | C42: =+C14+C19 -> 0 | D42: =+B42-C42 -> 0 | E42: =IFERROR((+D42*100/B42),0) -> 0 | G42: =+G14+G19 -> 0 | H42: =+H14+H19 -> 0 | I42: =+G42-H42 -> 0 | J42: =IFERROR((+I42*100/G42),0) -> 0
A43: Net Profit / (Loss) | B43: =+B8-B42 -> 0 | C43: =+C8-C42 -> 0 | D43: =+B43-C43 -> 0 | E43: =IFERROR((+D43*100/B43),0) -> 0 | G43: =+G8-G42 -> 0 | H43: =+H8-H42 -> 0 | I43: =+G43-H43 -> 0 | J43: =IFERROR((+I43*100/G43),0) -> 0

Sheet Job P&L
A2: =Cover!A9 -> Afrodiva Exotic Hair Boutique Ltd.
A3: =Cover!A10 -> DUABI UAE
Y4: Your Accounting & Tax Expert
A5: Job wist profit and Loss for the month of Jan 2108
A6: ="For The Period " -> For The Period
A8: Projects | B8: Dubai Land | C8: DubaiLand | D8: EA38 | E8: EA40 | F8: EA49 | G8: EA50 | H8: EA51 | I8: EA52 | J8: EA54 | K8: EA55 | L8: EA56 | M8: EA57 | N8: EA59 | O8: EA60 | P8: EA61 | Q8: EA62-001 | R8: EA62-003 | S8: EA62-004 | T8: EA62-005 | U8: EA62-Main | V8: EA63 | W8: General | X8: JV001 | Y8: JV002 | Z8: Jv003 | AA8: JV-Main | AB8: Grand Total
A9: Income
A10: Sales Income | Q10: 14500 | R10: 97500 | S10: 75000 | T10: 20000 | U10: 640000 | AB10: =SUM(B10:AA10) -> 847000
A11: Other Income | W11: 686.85 | AB11: =SUM(B11:AA11) -> 686.85
A12: Total Income | B12: 0 | C12: 0 | D12: 0 | E12: 0 | F12: 0 | G12: 0 | H12: 0 | I12: 0 | J12: 0 | K12: 0 | L12: 0 | M12: 0 | N12: 0 | O12: 0 | P12: 0 | Q12: 14500 | R12: 97500 | S12: 75000 | T12: 20000 | U12: 640000 | V12: 0 | W12: 686.85 | X12: 0 | Y12: 0 | Z12: 0 | AA12: 0 | AB12: =SUM(B12:AA12) -> 847686.85
AB13: =SUM(B13:AA13) -> 0
A14: A/C Works - Costs | P14: 31250 | AB14: =SUM(B14:AA14) -> 31250
A15: Anti Termite Proofing Service | Z15: 454 | AB15: =SUM(B15:AA15) -> 454
A16: Auditing Expenses | W16: 4500 | AB16: =SUM(B16:AA16) -> 4500
A17: Blocks Costs | L17: 2304 | U17: 2304 | V17: 3483 | AB17: =SUM(B17:AA17) -> 8091
A18: Car Service Expense | W18: 500 | AB18: =SUM(B18:AA18) -> 500
A19: Cement Costs | E19: 300 | J19: 1837.5 | L19: 1150 | M19: 1150 | N19: 1150 | P19: 2987.5 | U19: 1150 | Z19: 900 | AB19: =SUM(B19:AA19) -> 10625
A20: Chemicals & Bitumen Costs | M20: 1010 | P20: 720 | Y20: 2400 | AB20: =SUM(B20:AA20) -> 4130
A21: Concrete Costs | G21: 2624 | K21: 4324 | M21: 4262 | N21: 2530 | P21: 2730 | Y21: 15397 | Z21: 11040 | AB21: =SUM(B21:AA21) -> 42907
A22: Concrete Cutting Works-Costs | U22: 57456 | AB22: =SUM(B22:AA22) -> 57456
A23: Concrete Jacketing Works-Costs | U23: 54268.6 | AB23: =SUM(B23:AA23) -> 54268.6
A24: DM Fees | H24: 235 | L24: 1488.82 | N24: 125 | O24: 120 | AB24: =SUM(B24:AA24) -> 1968.82
A25: Electrical Materials-Costs | I25: 110 | K25: 14972.98 | L25: 3805.21 | N25: 19974.53 | P25: 3889.33 | W25: 816 | Z25: 200 | AB25: =SUM(B25:AA25) -> 43768.05
A26: Electrical Works-Costs | B26: 5160 | D26: 7500 | F26: 1890 | N26: 26075 | AB26: =SUM(B26:AA26) -> 40625
A27: Employee Benefit Expenses | W27: 290 | AB27: =SUM(B27:AA27) -> 290
A28: Equipment Rental Costs | B28: 7020 | F28: 825 | G28: 900 | H28: 2940 | J28: 630 | K28: 4675 | L28: 2250 | M28: 2325 | N28: 8905 | P28: 840 | Q28: 1400 | U28: 7750 | AB28: =SUM(B28:AA28) -> 40460
A29: Fines & Registrations Expense | W29: 175 | AB29: =SUM(B29:AA29) -> 175
A30: Fire Alarm&Fire Fighting Works | N30: 96000 | AB30: =SUM(B30:AA30) -> 96000
A31: Labor Costs | D31: 1344 | E31: 1306 | F31: 3118 | G31: 1529 | H31: 6969 | I31: 3462 | J31: 6109 | K31: 5694 | L31: 10417 | M31: 3430 | N31: 28279 | O31: 776 | P31: 15539 | U31: 5808 | V31: 4075 | W31: 2125 | X31: 9415 | Y31: 15006 | Z31: 31747 | AA31: 24800 | AB31: =SUM(B31:AA31) -> 180948
A32: Leave Salary | W32: 2400 | AB32: =SUM(B32:AA32) -> 2400
A33: Materials Costs | H33: 420 | J33: 22469.38 | K33: 3450 | M33: 310 | N33: 1450 | P33: 21773 | U33: 2850 | V33: 2818.8 | Y33: 4409 | Z33: 10983 | AB33: =SUM(B33:AA33) -> 70933.18
A34: Office Expense | M34: 6 | W34: 1143.52 | AB34: =SUM(B34:AA34) -> 1149.52
A35: Office Salary | F35: 16740.31 | G35: 16740.31 | H35: 16740.31 | J35: 16740.31 | K35: 16740.31 | L35: 16740.31 | M35: 16740.31 | N35: 16740.31 | P35: 16740.31 | U35: 16740.31 | V35: 16740.9 | W35: 645 | AB35: =SUM(B35:AA35) -> 184789
A36: Painting Mat. Supply - Costs | M36: 60 | O36: 570 | P36: 299 | AB36: =SUM(B36:AA36) -> 929
A37: Petrol Expenses | M37: 335 | U37: 100 | W37: 10093.15 | AB37: =SUM(B37:AA37) -> 10528.15
A38: Plastering Work Internal-Costs | C38: 4845 | P38: 16156.8 | AB38: =SUM(B38:AA38) -> 21001.8
A39: Plumbing Materials-Costs | H39: 3321.5 | I39: 2678 | K39: 42.5 | L39: 2895.55 | N39: 15090.55 | P39: 1154.5 | X39: 3644 | AB39: =SUM(B39:AA39) -> 28826.6
A40: RTA Fees | W40: 665 | AB40: =SUM(B40:AA40) -> 665
A41: Safety Equip. & Mat.- Costs | Z41: 192 | AB41: =SUM(B41:AA41) -> 192
A42: Sand Costs | F42: 1100 | H42: 2180 | I42: 2140 | J42: 1270 | K42: 2250 | L42: 680 | M42: 270 | N42: 8080 | P42: 3780 | U42: 270 | V42: 1100 | Y42: 4150 | Z42: 1150 | AB42: =SUM(B42:AA42) -> 28420
A43: Soil Testing Costs | G43: 32 | Y43: 72 | Z43: 104 | AB43: =SUM(B43:AA43) -> 208
A44: Ticket Expenses | W44: 2809.72 | AB44: =SUM(B44:AA44) -> 2809.72
A45: Tiles-Costs | P45: 26826.75 | AB45: =SUM(B45:AA45) -> 26826.75
A46: Utilities Expense | H46: 240 | N46: 300 | U46: 960 | V46: 140 | W46: 21.75 | AB46: =SUM(B46:AA46) -> 1661.75
A47: Visa Expenses | W47: 26693 | AB47: =SUM(B47:AA47) -> 26693
A48: Waste Collection-Costs | N48: 1520 | Y48: 2430 | AB48: =SUM(B48:AA48) -> 3950
A49: Water - Costs | N49: 280 | V49: 300 | X49: 3250 | Y49: 8700 | Z49: 3600 | AB49: =SUM(B49:AA49) -> 16130
A50: Waterproofing Works-Costs | G50: 60764 | AB50: =SUM(B50:AA50) -> 60764
A51: Total Cost | B51: =SUM(B14:B50) -> 12180 | C51: =SUM(C14:C50) -> 4845 | D51: =SUM(D14:D50) -> 8844 | E51: =SUM(E14:E50) -> 1606 | F51: =SUM(F14:F50) -> 23673.31 | G51: =SUM(G14:G50) -> 82589.31 | H51: =SUM(H14:H50) -> 33045.81 | I51: =SUM(I14:I50) -> 8390 | ... AA51: =SUM(AA14:AA50) -> 24800 | AB51: =SUM(B51:AA51) -> 1107293.9
AB52: =SUM(B52:AA52) -> 0
A53: P& L Job wise | B53: =B12-B51 -> -12180 | C53: =C12-C51 -> -4845 | D53: =D12-D51 -> -8844 | E53: =E12-E51 -> -1606 | F53: =F12-F51 -> -23673.31 | G53: =G12-G51 -> -82589.31 | H53: =H12-H51 -> -33045.81 | I53: =I12-I51 -> -8390 | ... AA53: =AA12-AA51 -> -24800 | AB53: =SUM(B53:AA53) -> -259607.09

Sheet SOCF
A2: =Cover!A9 -> Afrodiva Exotic Hair Boutique Ltd.
A3: =Cover!A10 -> DUABI UAE
A5: CASH FLOW STATEMENT
A6: =Galance!D20 -> For the month of January - 2026
A8: Amount in AED
A9: Particulars | D9: Note | F9: =SOCI!F8 -> 46023 | H9: =SOCI!I8 -> 45992 | J9: YTD
A11: CASH FLOWS FROM OPERATING ACTIVITIES
A12: Pre Tax Profit / (Loss)
A13: Adjustments for:
B14: Depreciation | F14: =INDEX(SOCI!$F$10:$I$48,MATCH(SOCF!$B$14,SOCI!$B$10:$B$48,0),MATCH(SOCF!$F$9,SOCI!$F$8:$I$8,0)) -> 12500 | H14: 0 | J14: 0
A15: Operating profit before working capital changes | F15: =SUM(F14:F14) -> 12500 | H15: =SUM(H14:H14) -> 0 | J15: =SUM(J14:J14) -> 0
A16: WORKING CAPITAL CHANGES
A17: (Increase) / decrease in current assets
B18: Cash in hand | F18: 0 | H18: 0 | J18: 0
B19: Bank Accounts | F19: 0 | H19: 0 | J19: 0
B20: Accounts receivable | F20: 0 | H20: 0 | J20: 0
B21: Advance Paid to creditors | F21: 0 | H21: 0 | J21: 0
B22: Prepaid Expenses | F22: 0 | H22: 0 | J22: 0
B23: Loans, Advance & Deposists | F23: 0 | H23: 0 | J23: 0
B24: Cheque in transit | F24: =SOFP!H25-SOFP!E25 -> #VALUE! | H24: =SOFP!J25-SOFP!H25 -> #VALUE! | J24: =SOFP!L25-SOFP!J25 -> 0
F25: =SUM(F18:F24) -> #VALUE! | H25: =SUM(H18:H24) -> #VALUE! | J25: =SUM(J18:J24) -> 0
A26: Increase / (decrease) in current liabilities
B27: Commission payable - Agent | F27: 0 | H27: 0 | J27: 0
B28: Commission payable - Third party | F28: 0 | H28: 0 | J28: 0
B29: Statutory Liabilities | F29: 0 | H29: 0 | J29: 0
B30: Duties & Taxes Payable | F30: 0 | H30: 0 | J30: 0
B31: Accounts Payable | F31: 0 | H31: 0 | J31: 0
F32: =SUM(F27:F31) -> 0 | H32: =SUM(H27:H31) -> 0 | J32: =SUM(J27:J31) -> 0
A33: Cash generated from operations | F33: =F15+F25+F32 -> #VALUE! | H33: =H15+H25+H32 -> #VALUE! | J33: =J15+J25+J32 -> 0
A34: Taxes paid (less)
A35: Net cash outflows from operating activities | F35: =SUM(F33:F34) -> #VALUE! | H35: =SUM(H33:H34) -> #VALUE! | J35: =SUM(J33:J34) -> 0
A36: CASH FLOWS FROM INVESTING ACTIVITIES
A37: (Increase) / decrease in fixed and non-current assets
B38: Owned property and quipment (cost) | F38: 0 | H38: 0 | J38: 0
B39: Investments | F39: 0 | H39: 0 | J39: 0
B40: Deferred Assets | F40: 0 | H40: 0 | J40: 0
A41: Net cash outflows from investing activities | F41: =SUM(F38:F40) -> 0 | H41: =SUM(H38:H40) -> 0 | J41: =SUM(J38:J40) -> 0
A42: CASH FLOWS FROM FINANCING ACTIVITIES
A43: Increase / (decrease) in equity and non-current liabilities
B44: Capital A/C KW | F44: 0 | H44: 0 | J44: 0
B45: Capital A/C MJV | F45: 0 | H45: 0 | J45: 0
B46: Current A/C KW | F46: 0 | H46: 0 | J46: 0
B47: Current A/C MJV | F47: 0 | H47: 0 | J47: 0
B48: Loan form bank | F48: 0 | H48: 0 | J48: 0
B49: Auto Loan | F49: 0 | H49: 0 | J49: 0
B50: Other Loans | F50: 0 | H50: 0 | J50: 0
A51: Net cash outflows from financing activities | F51: =SUM(F44:F50) -> 0 | H51: =SUM(H44:H50) -> 0 | J51: =SUM(J44:J50) -> 0
A52: Net increase / (decrease) in cash and cash quivalents | F52: =F51+F41+F35 -> #VALUE! | H52: =H51+H41+H35 -> #VALUE! | J52: =J51+J41+J35 -> 0
A53: Cash and cash equivalents at the start
A54: Cash and cash equivalents at the end | F54: =SUM(F52:F53) -> #VALUE! | H54: =SUM(H52:H53) -> #VALUE! | J54: =SUM(J52:J53) -> 0

Sheet Linked IS
B1: DIFC | C1: Al Barsha
A2: Account Description | B2: Jan-2026 | C2: Jan-2026
A3: Revenues
A4: Sales | B4: 87643.893 | E4: 262931.68 | F4: =E4/3 -> 87643.893
A5: E-Commerce's/Online Sale
A6: Other Income | E6: =B14/B4*100 -> 39.985851
A7: Sales Discounts
A8: Total Revenues | B8: =ROUND(SUBTOTAL(9, B3:B6)-B7, 5) -> 87643.893 | C8: =ROUND(SUBTOTAL(9, C3:C6)-C7, 5) -> 0
A10: Cost of Sale
A11: Opening Stock | B11: 130480.9 | E11: 43493.633
A12: Purchases | B12: 13053.257 | E12: 13053.257
A13: Closing Stock | B13: 108489 | E13: 21489.333
A14: Cost of Sales | B14: =B11+B12-B13 -> 35045.157 | E14: 35057.557
A15: Gross Profit | B15: =-(ROUND(-B8+B14, 5)) -> 52598.737 | C15: =-(ROUND(-C8+C14, 5)) -> 0
A17: Operating and Administrative Expenses
A18: Salary & wages | B18: 0
A19: Admin. Expenses | B19: 85.666667 | E19: 85.666667 | F19: 85.666667
A20: Legal & Professional Consultancy Service fee | B20: 2000 | E20: 2000 | F20: 2000
A21: Office Misc. Expenses | B21: 0 | E21: 0 | F21: 0
A22: Trade License & Legal Expenses | B22: 0 | E22: 0 | F22: 0
A23: Office Rent Expenses | B23: 0 | E23: 0 | F23: 0
A24: Utility Expenses | B24: 0 | E24: 0 | F24: 0
A25: Printing & Stationery | B25: 1193.5 | E25: 1193.5 | F25: 1193.5
A26: Meals & Refreshments General | B26: 265.51333 | E26: 265.51333 | F26: 265.51333
A27: Staff Medical Expenses | B27: 4.8333333 | E27: 4.8333333 | F27: 4.8333333
A28: Travel & Transportation Expenses | B28: 511.33333 | E28: 511.33333 | F28: 511.33333
A29: Employee's Visa Expenses. | B29: 1503.7533 | E29: 1503.7533 | F29: 1503.7533
A30: Advertisement & Marketing Expenses | B30: 1200 | E30: 1200 | F30: 1200
... A32: Delivery Charges expenses | B32: 12.333333 | E32: 12.333333 | F32: 12.333333
A33: Total Expenses | B33: =ROUND(SUBTOTAL(9, B18:B32), 5) -> 6797.81 | C33: =ROUND(SUBTOTAL(9, C17:C32), 5) -> 0
A35: Other Expenses
A36: Directors’ Remuneration | B36: 50000 | E36: 50000 | F36: 50000
A37: Bank Charges | B37: 0
A38: WPS Charges | B38: 0
A39: Interest on Loans | B39: 0
A40: Fines & Mukhalfa | B40: 0
A41: Depreciation | B41: 12500
A42: Total Other Expenses | B42: =ROUND(SUBTOTAL(9, B35:B41), 5) -> 62500 | C42: =ROUND(SUBTOTAL(9, C35:C41), 5) -> 0
A45: Net Profit / Loss | B45: =B15-B33-B42 -> -16699.073 | C45: =C8-C15-C33-C42 -> 0

Sheet Linked BS
B1: Company Name
B2: Balance Sheet
B3: 30 Oct 2023
A5: MIS Flag
B6: ASSETS | C6: DIFC | D6: Al Barsha | E6: Total
B7: Current Assets | E7: =SUM(C7:D7) -> 0
A8: Cash in hand | B8: Trade & other receivables | C8: 0 | E8: =SUM(C8:D8) -> 0
A9: Bank Accounts | B9: Inventory | C9: ='Linked IS'!B13 -> 108489 | E9: =SUM(C9:D9) -> 108489
A10: Accounts receivable (Net) | B10: Security Deposit | C10: 0 | E10: =SUM(C10:D10) -> 0
A11: Accounts receivable (Net) | B11: Employee Advances | C11: 0 | E11: =SUM(C11:D11) -> 0
A12: VAT Input (Receivable) | B12: Prepayments & Prepaid Expenses | C12: 15583.33 | E12: =SUM(C12:D12) -> 15583.33
A13: Loans, Advance & Deposists | B13: Cash and cash equivalents | E13: =SUM(C13:D13) -> 0
A14: Loans, Advance & Deposists | B14: Cash In Hand Vanissa | E14: =SUM(C14:D14) -> 0
A15: Loans, Advance & Deposists | B15: Cash In Hand Omotola | E15: =SUM(C15:D15) -> 0
A16: JV (Internal) | B16: Bank | C16: 69576 | E16: =SUM(C16:D16) -> 69576
A17: Advance Paid to suppliers | B17: InPut VAT | E17: =SUM(C17:D17) -> 0
A18: Loans, Advance & Deposists | E18: =SUM(C18:D18) -> 0
B19: Total Current Assets | C19: =SUM(C8:C18) -> 193648.33 | E19: =SUM(C19:D19) -> 193648.33
E20: =SUM(C20:D20) -> 0
B21: Non Current Assets | E21: =SUM(C21:D21) -> 0
B22: Office Fit Out | C22: =456000-12500 -> 443500 | E22: =SUM(C22:D22) -> 443500
A23: Property and equipement | B23: Computer and Electronics | E23: =SUM(C23:D23) -> 0
E24: =SUM(C24:D24) -> 0
B25: Total Non Current Assets | C25: =SUM(C22:C24) -> 443500 | E25: =SUM(C25:D25) -> 443500
E26: =SUM(C26:D26) -> 0
B27: Total Assets | C27: =C19+C25 -> 637148.33 | E27: =SUM(C27:D27) -> 637148.33
E28: =SUM(C28:D28) -> 0
B29: LIABILITIES AND CAPITAL | E29: =SUM(C29:D29) -> 0
E30: =SUM(C30:D30) -> 0
A31: Accounts Payable (Net) | B31: Current Liabilities | C31: 650000 | E31: =SUM(C31:D31) -> 650000
A32: Salary and Wages Payable | B32: Trade & other payables | E32: =SUM(C32:D32) -> 0
A33: Accounts Payable (Net) | B33: OutPut VAT | C33: ='Linked IS'!B4*0.05 -> 4382.1947 | E33: =SUM(C33:D33) -> 4382.1947
A34: VAT Output (Payable) | E34: =SUM(C34:D34) -> 0
B35: Total Current Liabilities | C35: =SUM(C31:C34) -> 654382.19 | E35: =SUM(C35:D35) -> 654382.19
E36: =SUM(C36:D36) -> 0
B37: Long Term Liabilities | E37: =SUM(C37:D37) -> 0
E38: =SUM(C38:D38) -> 0
A39: Capital A/C | B39: Share capital | C39: 183500 | E39: =SUM(C39:D39) -> 183500
A40: Omar Shubair-C/A | B40: Shareholder's current account | C40: -371049.79 | E40: =SUM(C40:D40) -> -371049.79
A41: Retained Earnings | B41: Retained Earnings | C41: 187015 | E41: =SUM(C41:D41) -> 187015
B42: profit and loss | C42: ='Linked IS'!B45 -> -16699.073 | E42: =SUM(C42:D42) -> -16699.073
B43: Total Long Term Liabilities | C43: =SUM(C39:C42) -> -17233.863 | D43: =SUM(D39:D42) -> 0 | E43: =SUM(C43:D43) -> -17233.863
E44: =SUM(C44:D44) -> 0
B45: Total Liabilities & Capital | C45: =C43+C35 -> 637148.33 | D45: =D43+D35 -> 0 | E45: =SUM(C45:D45) -> 637148.33
C46: =C27-C45 -> -0.0013266667 | D46: =D27-D45 -> 0 | E46: =E27-E45 -> -0.0013266667
